Workbook
Name Slicer_Month_Name: #N/A
Name Slicer_Month_Year: #N/A
Name Slicer_Ticket_Status: #N/A
Name Slicer_Ticket_Type: #N/A

Sheet Working data
A1: Ticket ID | B1: Customer Name | C1: Customer Email | D1: Customer Age | E1: Customer Gender | F1: Product Purchased | G1: Date of Purchase | H1: Ticket Type | I1: Ticket Subject | J1: Ticket Description | K1: Ticket Status | L1: Resolution | M1: Ticket Priority | N1: Ticket Channel | O1: First Response Time | P1: Time to Resolution | Q1: Customer Satisfaction Rating | R1: Row check | S1: Resolution Clean | T1: Customer_Name_Clean | U1: Month_Number | V1: Month_Name | W1: Month_Year | X1: Resolution Time (Hours)
A2: 1 | B2: Marisa Obrien | C2: carrollallison@example.com | D2: 32 | E2: Other | F2: GoPro Hero | G2: 44277 | H2: Technical issue | I2: Product setup | J2: I'm having an issue with the {product_purchased}. Please assist. Your billing zip code is: 71701. We appreciate that you have requested a website address. Please double check your email address. I've tried troubleshooting steps mentioned in the user manual, but the issue persists. | K2: Pending Customer Response | M2: Critical | N2: Social media | O2: 45078.511 | R2: 1 | S2: =PROPER(CustomerSupport[[#This Row],[Resolution]]) | T2: =TRIM(CustomerSupport[[#This Row],[Customer Name]]) -> Marisa Obrien | U2: =MONTH(CustomerSupport[[#This Row],[Date of Purchase]]) -> 3 | V2: =TEXT('Working data'!G2,"mmmm") -> March | W2: =YEAR(CustomerSupport[[#This Row],[Date of Purchase]]) -> 2021 | X2: =IF(OR(O2="",P2=""),"",(P2-O2)*24)
A3: 2 | B3: Jessica Rios | C3: clarkeashley@example.com | D3: 42 | E3: Female | F3: LG Smart TV | G3: 44338 | H3: Technical issue | I3: Peripheral compatibility | J3: I'm having an issue with the {product_purchased}. Please assist. If you need to change an existing product. I'm having an issue with the {product_purchased}. Please assist. If The issue I'm facing is intermittent. Sometimes it works fine, but other times it acts up unexpectedly. | K3: Pending Customer Response | M3: Critical | N3: Chat | O3: 45078.698 | R3: 2 | S3: =PROPER(CustomerSupport[[#This Row],[Resolution]]) | T3: =TRIM(CustomerSupport[[#This Row],[Customer Name]]) -> Jessica Rios | U3: =MONTH(CustomerSupport[[#This Row],[Date of Purchase]]) -> 5 | V3: =TEXT('Working data'!G3,"mmmm") -> May | W3: =YEAR(CustomerSupport[[#This Row],[Date of Purchase]]) -> 2021 | X3: =IF(OR(O3="",P3=""),"",(P3-O3)*24)
A4: 3 | B4: Christopher Robbins | C4: gonzalestracy@example.com | D4: 48 | E4: Other | F4: Dell XPS | G4: 44026 | H4: Technical issue | I4: Network problem | J4: I'm facing a problem with my {product_purchased}. The {product_purchased} is not turning on. It was working fine until yesterday, but now it doesn't respond. 1.8.3 I really I'm using the original charger that came with my {product_purchased}, but it's not charging properly. | K4: Closed | L4: Case maybe show recently my computer follow. | M4: Low | N4: Social media | O4: 45078.468 | P4: 45078.754 | Q4: 3 | R4: 3 | S4: =PROPER(CustomerSupport[[#This Row],[Resolution]]) -> Case Maybe Show Recently My Computer Follow. | T4: =TRIM(CustomerSupport[[#This Row],[Customer Name]]) -> Christopher Robbins | U4: =MONTH(CustomerSupport[[#This Row],[Date of Purchase]]) -> 7 | V4: =TEXT('Working data'!G4,"mmmm") -> July | W4: =YEAR(CustomerSupport[[#This Row],[Date of Purchase]]) -> 2020 | X4: =IF(OR(O4="",P4=""),"",(P4-O4)*24) -> 6.85
A5: 4 | B5: Christina Dillon | C5: bradleyolson@example.org | D5: 27 | E5: Female | F5: Microsoft Office | G5: 44148 | H5: Billing inquiry | I5: Account access | J5: I'm having an issue with the {product_purchased}. Please assist. If you have a problem you're interested in and I'd love to see this happen, please check out the Feedback. I've already contacted customer support multiple times, but the issue remains unresolved. | K5: Closed | L5: Try capital clearly never color toward story. | M5: Low | N5: Social media | O5: 45078.312 | P5: 45078.082 | Q5: 3 | R5: 4 | S5: =PROPER(CustomerSupport[[#This Row],[Resolution]]) -> Try Capital Clearly Never Color Toward Story. | T5: =TRIM(CustomerSupport[[#This Row],[Customer Name]]) -> Christina Dillon | U5: =MONTH(CustomerSupport[[#This Row],[Date of Purchase]]) -> 11 | V5: =TEXT('Working data'!G5,"mmmm") -> November | W5: =YEAR(CustomerSupport[[#This Row],[Date of Purchase]]) -> 2020 | X5: =IF(OR(O5="",P5=""),"",(P5-O5)*24) -> -5.5333333
A6: 5 | B6: Alexander Carroll | C6: bradleymark@example.com | D6: 67 | E6: Female | F6: Autodesk AutoCAD | G6: 43865 | H6: Billing inquiry | I6: Data loss | J6: I'm having an issue with the {product_purchased}. Please assist. Note: The seller is not responsible for any damages arising out of the delivery of the battleground game. Please have the game in good condition and shipped to you I've noticed a sudden decrease in battery life on my {product_purchased}. It used to last much longer. | K6: Closed | L6: West decision evidence bit. | M6: Low | N6: Email | O6: 45078.009 | P6: 45078.829 | Q6: 1 | R6: 5 | S6: =PROPER(CustomerSupport[[#This Row],[Resolution]]) -> West Decision Evidence Bit. | T6: =TRIM(CustomerSupport[[#This Row],[Customer Name]]) -> Alexander Carroll | U6: =MONTH(CustomerSupport[[#This Row],[Date of Purchase]]) -> 2 | V6: =TEXT('Working data'!G6,"mmmm") -> February | W6: =YEAR(CustomerSupport[[#This Row],[Date of Purchase]]) -> 2020 | X6: =IF(OR(O6="",P6=""),"",(P6-O6)*24) -> 19.683333
A7: 6 | B7: Rebecca Fleming | C7: sheenasmith@example.com | D7: 53 | E7: Male | F7: Microsoft Office | G7: 44040 | H7: Cancellation request | I7: Payment issue | J7: I'm facing a problem with my {product_purchased}. The {product_purchased} is not turning on. It was working fine until yesterday, but now it doesn't respond. To remove the new {product_purch I've checked for any available software updates for my {product_purchased}, but there are none. | K7: Open | M7: Low | N7: Social media | R7: 6 | S7: =PROPER(CustomerSupport[[#This Row],[Resolution]]) | T7: =TRIM(CustomerSupport[[#This Row],[Customer Name]]) -> Rebecca Fleming | U7: =MONTH(CustomerSupport[[#This Row],[Date of Purchase]]) -> 7 | V7: =TEXT('Working data'!G7,"mmmm") -> July | W7: =YEAR(CustomerSupport[[#This Row],[Date of Purchase]]) -> 2020 | X7: =IF(OR(O7="",P7=""),"",(P7-O7)*24)
A8: 7 | B8: Jacqueline Wright | C8: donaldkeith@example.org | D8: 24 | E8: Other | F8: Microsoft Surface | G8: 43884 | H8: Product inquiry | I8: Refund request | J8: I'm unable to access my {product_purchased} account. It keeps displaying an 'Invalid Credentials' error, even though I'm using the correct login information. How can I regain access to my account? Solution 1 I'm unable to find the option to perform the desired action in the {product_purchased}. Could you please guide me through the steps? | K8: Open | M8: Critical | N8: Social media | R8: 7 | S8: =PROPER(CustomerSupport[[#This Row],[Resolution]]) | T8: =TRIM(CustomerSupport[[#This Row],[Customer Name]]) -> Jacqueline Wright | U8: =MONTH(CustomerSupport[[#This Row],[Date of Purchase]]) -> 2 | V8: =TEXT('Working data'!G8,"mmmm") -> February | W8: =YEAR(CustomerSupport[[#This Row],[Date of Purchase]]) -> 2020 | X8: =IF(OR(O8="",P8=""),"",(P8-O8)*24)
A9: 8 | B9: Denise Lee | C9: joelwilliams@example.com | D9: 23 | E9: Male | F9: Philips Hue Lights | G9: 44052 | H9: Refund request | I9: Battery life | J9: I'm having an issue with the {product_purchased}. Please assist. (Thanks) I will contact all my suppliers and confirm. Please try and find out whether their inventory is currently stocked, or any other reason. I am I've performed a factory reset on my {product_purchased}, hoping it would resolve the problem, but it didn't help. | K9: Open | M9: Critical | N9: Social media | R9: 8 | S9: =PROPER(CustomerSupport[[#This Row],[Resolution]]) | T9: =TRIM(CustomerSupport[[#This Row],[Customer Name]]) -> Denise Lee | U9: =MONTH(CustomerSupport[[#This Row],[Date of Purchase]]) -> 8 | V9: =TEXT('Working data'!G9,"mmmm") -> August | W9: =YEAR(CustomerSupport[[#This Row],[Date of Purchase]]) -> 2020 | X9: =IF(OR(O9="",P9=""),"",(P9-O9)*24)
A10: 9 | B10: Nicolas Wilson | C10: joshua24@example.com | D10: 60 | E10: Other | F10: Fitbit Versa Smartwatch | G10: 44028 | H10: Technical issue | I10: Installation support | J10: I'm having an issue with the {product_purchased}. Please assist. Thank you. {product_purchased} is not the exact type you might prefer, they use the exact same method for different uses. Please help I've recently updated the firmware of my {product_purchased}, and the issue started happening afterward. Could it be related to the update? | K10: Pending Customer Response | M10: Low | N10: Social media | O10: 45078.439 | R10: 9 | S10: =PROPER(CustomerSupport[[#This Row],[Resolution]]) | T10: =TRIM(CustomerSupport[[#This Row],[Customer Name]]) -> Nicolas Wilson | U10: =MONTH(CustomerSupport[[#This Row],[Date of Purchase]]) -> 7 | V10: =TEXT('Working data'!G10,"mmmm") -> July | W10: =YEAR(CustomerSupport[[#This Row],[Date of Purchase]]) -> 2020 | X10: =IF(OR(O10="",P10=""),"",(P10-O10)*24)
A11: 10 | B11: William Dawson | C11: clopez@example.com | D11: 27 | E11: Male | F11: Dyson Vacuum Cleaner | G11: 43896 | H11: Refund request | I11: Payment issue | J11: My {product_purchased} is making strange noises and not functioning properly. I suspect there might be a hardware issue. Can you please help me with this? } If we can, please send a "request" to dav The issue I'm facing is intermittent. Sometimes it works fine, but other times it acts up unexpectedly. | K11: Pending Customer Response | M11: Critical | N11: Phone | O11: 45078.393 | R11: 10 | S11: =PROPER(CustomerSupport[[#This Row],[Resolution]]) | T11: =TRIM(CustomerSupport[[#This Row],[Customer Name]]) -> William Dawson | U11: =MONTH(CustomerSupport[[#This Row],[Date of Purchase]]) -> 3 | V11: =TEXT('Working data'!G11,"mmmm") -> March | W11: =YEAR(CustomerSupport[[#This Row],[Date of Purchase]]) -> 2020 | X11: =IF(OR(O11="",P11=""),"",(P11-O11)*24)
A12: 11 | B12: Joseph Moreno | C12: mbrown@example.org | D12: 48 | E12: Male | F12: Nintendo Switch | G12: 44215 | H12: Cancellation request | I12: Data loss | J12: I'm having an issue with the {product_purchased}. Please assist. 1-800-799-0808. Product Search: What's New in 2-3-4-5? Report Feedback Customer Service is your best I'm using the original charger that came with my {product_purchased}, but it's not charging properly. | K12: Closed | L12: Measure tonight surface feel forward. | M12: High | N12: Phone | O12: 45078.741 | P12: 45077.994 | Q12: 1 | R12: 11 | S12: =PROPER(CustomerSupport[[#This Row],[Resolution]]) -> Measure Tonight Surface Feel Forward. | T12: =TRIM(CustomerSupport[[#This Row],[Customer Name]]) -> Joseph Moreno | U12: =MONTH(CustomerSupport[[#This Row],[Date of Purchase]]) -> 1 | V12: =TEXT('Working data'!G12,"mmmm") -> January | W12: =YEAR(CustomerSupport[[#This Row],[Date of Purchase]]) -> 2021 | X12: =IF(OR(O12="",P12=""),"",(P12-O12)*24) -> -17.916667
A13: 12 | B13: Brandon Arnold | C13: davisjohn@example.net | D13: 51 | E13: Male | F13: Microsoft Xbox Controller | G13: 44493 | H13: Product inquiry | I13: Software bug | J13: I'm having an issue with the {product_purchased}. Please assist. 4. It is possible that we cannot find some type of text or a product name to identify someone like Mr. Brown. 5. On the I've reviewed the troubleshooting steps on the official support website, but they didn't resolve the problem. | K13: Closed | L13: Measure there house management pick knowledge trade. | M13: High | N13: Chat | O13: 45078.504 | P13: 45078.394 | Q13: 1 | R13: 12 | S13: =PROPER(CustomerSupport[[#This Row],[Resolution]]) -> Measure There House Management Pick Knowledge Trade. | T13: =TRIM(CustomerSupport[[#This Row],[Customer Name]]) -> Brandon Arnold | U13: =MONTH(CustomerSupport[[#This Row],[Date of Purchase]]) -> 10 | V13: =TEXT('Working data'!G13,"mmmm") -> October | W13: =YEAR(CustomerSupport[[#This Row],[Date of Purchase]]) -> 2021 | X13: =IF(OR(O13="",P13=""),"",(P13-O13)*24) -> -2.6333333
A14: 13 | B14: Tamara Hahn | C14: jensenwilliam@example.net | D14: 27 | E14: Other | F14: Nintendo Switch Pro Controller | G14: 44342 | H14: Technical issue | I14: Hardware issue | J14: I'm having an issue with the {product_purchased}. Please assist. CQW: Why didn't I send him the invoice? Thanks a lot. L: He's like the best customer I've met. I've noticed that the issue occurs consistently when I use a specific feature or application on my {product_purchased}. | K14: Pending Customer Response | M14: Low | N14: Chat | O14: 45078.794 | R14: 13 | S14: =PROPER(CustomerSupport[[#This Row],[Resolution]]) | T14: =TRIM(CustomerSupport[[#This Row],[Customer Name]]) -> Tamara Hahn | U14: =MONTH(CustomerSupport[[#This Row],[Date of Purchase]]) -> 5 | V14: =TEXT('Working data'!G14,"mmmm") -> May | W14: =YEAR(CustomerSupport[[#This Row],[Date of Purchase]]) -> 2021 | X14: =IF(OR(O14="",P14=""),"",(P14-O14)*24)
A15: 14 | B15: Sandra Barnes | C15: gwendolyn51@example.net | D15: 65 | E15: Other | F15: Nest Thermostat | G15: 44025 | H15: Technical issue | I15: Product setup | J15: I've recently set up my {product_purchased}, but it fails to connect to any available networks. What steps should I take to troubleshoot this issue? I can't find the 'Product_IP' field of the I'm concerned about the security of my {product_purchased} and would like to ensure that my data is safe. | K15: Pending Customer Response | M15: Low | N15: Chat | O15: 45078.858 | R15: 14 | S15: =PROPER(CustomerSupport[[#This Row],[Resolution]]) | T15: =TRIM(CustomerSupport[[#This Row],[Customer Name]]) -> Sandra Barnes | U15: =MONTH(CustomerSupport[[#This Row],[Date of Purchase]]) -> 7 | V15: =TEXT('Working data'!G15,"mmmm") -> July | W15: =YEAR(CustomerSupport[[#This Row],[Date of Purchase]]) -> 2020 | X15: =IF(OR(O15="",P15=""),"",(P15-O15)*24)
A16: 15 | B16: Amy Hill | C16: medinasteven@example.net | D16: 48 | E16: Female | F16: Sony PlayStation | G16: 43890 | H16: Billing inquiry | I16: Product setup | J16: I'm having an issue with the {product_purchased}. Please assist. Product Name: TPUBASK3E3KQ0 Join Date: Oct 2007 Posts: 11,532 Quote: I've recently updated the firmware of my {product_purchased}, and the issue started happening afterward. Could it be related to the update? | K16: Closed | L16: Officer moment world sing parent available. | M16: High | N16: Chat | O16: 45078.266 | P16: 45077.965 | Q16: 4 | R16: 15 | S16: =PROPER(CustomerSupport[[#This Row],[Resolution]]) -> Officer Moment World Sing Parent Available. | T16: =TRIM(CustomerSupport[[#This Row],[Customer Name]]) -> Amy Hill | U16: =MONTH(CustomerSupport[[#This Row],[Date of Purchase]]) -> 2 | V16: =TEXT('Working data'!G16,"mmmm") -> February | W16: =YEAR(CustomerSupport[[#This Row],[Date of Purchase]]) -> 2020 | X16: =IF(OR(O16="",P16=""),"",(P16-O16)*24) -> -7.2333333
A17: 16 | B17: Elizabeth Foley | C17: amy41@example.net | D17: 18 | E17: Other | F17: GoPro Action Camera | G17: 44371 | H17: Billing inquiry | I17: Product recommendation | J17: I'm having an issue with the {product_purchased}. Please assist. Please note, you might have already paid for this product, which means spectators are not buying any of the products from the sale as their donations will go straight I've noticed a sudden decrease in battery life on my {product_purchased}. It used to last much longer. | K17: Pending Customer Response | M17: High | N17: Social media | O17: 45078.632 | R17: 16 | S17: =PROPER(CustomerSupport[[#This Row],[Resolution]]) | T17: =TRIM(CustomerSupport[[#This Row],[Customer Name]]) -> Elizabeth Foley | U17: =MONTH(CustomerSupport[[#This Row],[Date of Purchase]]) -> 6 | V17: =TEXT('Working data'!G17,"mmmm") -> June | W17: =YEAR(CustomerSupport[[#This Row],[Date of Purchase]]) -> 2021 | X17: =IF(OR(O17="",P17=""),"",(P17-O17)*24)
A18: 17 | B18: Julia Salazar | C18: watkinsbarbara@example.com | D18: 63 | E18: Other | F18: Xbox | G18: 44482 | H18: Product inquiry | I18: Account access | J18: I'm having an issue with the {product_purchased}. Please assist. - Acknowledgement: Thanks to Dan for the tip. When you purchase a new product from my store or from your local retailer, they will also provide I'm concerned about the security of my {product_purchased} and would like to ensure that my data is safe. | K18: Closed | L18: Seek evidence book collection catch. | M18: Critical | N18: Chat | O18: 45078.824 | P18: 45078.666 | Q18: 4 | R18: 17 | S18: =PROPER(CustomerSupport[[#This Row],[Resolution]]) -> Seek Evidence Book Collection Catch. | T18: =TRIM(CustomerSupport[[#This Row],[Customer Name]]) -> Julia Salazar | U18: =MONTH(CustomerSupport[[#This Row],[Date of Purchase]]) -> 10 | V18: =TEXT('Working data'!G18,"mmmm") -> October | W18: =YEAR(CustomerSupport[[#This Row],[Date of Purchase]]) -> 2021 | X18: =IF(OR(O18="",P18=""),"",(P18-O18)*24) -> -3.8
A19: 18 | B19: Joshua Castillo | C19: mooredeborah@example.org | D19: 56 | E19: Female | F19: Microsoft Xbox Controller | G19: 44081 | H19: Product inquiry | I19: Payment issue | J19: I'm having an issue with the {product_purchased}. Please assist. Thanks!" * [0] - [0] - [0] - [0] If this product is sold and you have not used any I've reviewed the troubleshooting steps on the official support website, but they didn't resolve the problem. | K19: Pending Customer Response | M19: High | N19: Chat | O19: 45078.878 | R19: 18 | S19: =PROPER(CustomerSupport[[#This Row],[Resolution]]) | T19: =TRIM(CustomerSupport[[#This Row],[Customer Name]]) -> Joshua Castillo | U19: =MONTH(CustomerSupport[[#This Row],[Date of Purchase]]) -> 9 | V19: =TEXT('Working data'!G19,"mmmm") -> September | W19: =YEAR(CustomerSupport[[#This Row],[Date of Purchase]]) -> 2020 | X19: =IF(OR(O19="",P19=""),"",(P19-O19)*24)
A20: 19 | B20: Wendy Davis | C20: brenda20@example.net | D20: 19 | E20: Male | F20: LG Washing Machine | G20: 44462 | H20: Product inquiry | I20: Peripheral compatibility | J20: I'm having an issue with the {product_purchased}. Please assist. I want to be an active member of our community on YouTube... The issue I'm facing is intermittent. Sometimes it works fine, but other times it acts up unexpectedly. | K20: Open | M20: High | N20: Social media | R20: 19 | S20: =PROPER(CustomerSupport[[#This Row],[Resolution]]) | T20: =TRIM(CustomerSupport[[#This Row],[Customer Name]]) -> Wendy Davis | U20: =MONTH(CustomerSupport[[#This Row],[Date of Purchase]]) -> 9 | V20: =TEXT('Working data'!G20,"mmmm") -> September | W20: =YEAR(CustomerSupport[[#This Row],[Date of Purchase]]) -> 2021 | X20: =IF(OR(O20="",P20=""),"",(P20-O20)*24)
A21: 20 | B21: Jeffrey Robertson | C21: jameslopez@example.com | D21: 39 | E21: Female | F21: Canon EOS | G21: 44263 | H21: Refund request | I21: Software bug | J21: I'm having an issue with the {product_purchased}. Please assist. I'm having an issue with the product_purchased}. Please assist. Customer Reviewer: My Husband was able to take an order from Apple I've checked for any available software updates for my {product_purchased}, but there are none. | K21: Closed | L21: Wish mouth build resource though. | M21: Low | N21: Chat | O21: 45078.032 | P21: 45078.854 | Q21: 5 | R21: 20 | S21: =PROPER(CustomerSupport[[#This Row],[Resolution]]) -> Wish Mouth Build Resource Though. | T21: =TRIM(CustomerSupport[[#This Row],[Customer Name]]) -> Jeffrey Robertson | U21: =MONTH(CustomerSupport[[#This Row],[Date of Purchase]]) -> 3 | V21: =TEXT('Working data'!G21,"mmmm") -> March | W21: =YEAR(CustomerSupport[[#This Row],[Date of Purchase]]) -> 2021 | X21: =IF(OR(O21="",P21=""),"",(P21-O21)*24) -> 19.716667
A22: 21 | B22: Suzanne Holmes | C22: rogermcgrath@example.net | D22: 28 | E22: Other | F22: HP Pavilion | G22: 44347 | H22: Refund request | I22: Payment issue | J22: I'm having an issue with the {product_purchased}. Please assist. " -name "Microsoft Surface Pro. " " -version 1.10.2 "1.10.2" " -usage I've checked for any available software updates for my {product_purchased}, but there are none. | K22: Pending Customer Response | M22: High | N22: Chat | O22: 45078.214 | R22: 21 | S22: =PROPER(CustomerSupport[[#This Row],[Resolution]]) | T22: =TRIM(CustomerSupport[[#This Row],[Customer Name]]) -> Suzanne Holmes | U22: =MONTH(CustomerSupport[[#This Row],[Date of Purchase]]) -> 5 | V22: =TEXT('Working data'!G22,"mmmm") -> May | W22: =YEAR(CustomerSupport[[#This Row],[Date of Purchase]]) -> 2021 | X22: =IF(OR(O22="",P22=""),"",(P22-O22)*24)
A23: 22 | B23: Tanner Conley | C23: zbond@example.net | D23: 66 | E23: Male | F23: Fitbit Versa Smartwatch | G23: 43865 | H23: Cancellation request | I23: Installation support | J23: I'm having an issue with the {product_purchased}. Please assist. The email address should change to: customer@julietr.com, as there is a unique id number unique for each product. You I've tried different settings and configurations on my {product_purchased}, but the issue persists. | K23: Pending Customer Response | M23: Critical | N23: Social media | O23: 45077.998 | R23: 22 | S23: =PROPER(CustomerSupport[[#This Row],[Resolution]]) | T23: =TRIM(CustomerSupport[[#This Row],[Customer Name]]) -> Tanner Conley | U23: =MONTH(CustomerSupport[[#This Row],[Date of Purchase]]) -> 2 | V23: =TEXT('Working data'!G23,"mmmm") -> February | W23: =YEAR(CustomerSupport[[#This Row],[Date of Purchase]]) -> 2020 | X23: =IF(OR(O23="",P23=""),"",(P23-O23)*24)
A24: 23 | B24: Stephanie Nelson DVM | C24: ljohnson@example.org | D24: 54 | E24: Female | F24: Xbox | G24: 43872 | H24: Cancellation request | I24: Delivery problem | J24: I'm having an issue with the {product_purchased}. Please assist. (And if need be this time, that could help.) 1.3.2.1 Update my version to 3.0 or more. The issue I'm facing is intermittent. Sometimes it works fine, but other times it acts up unexpectedly. | K24: Open | M24: Medium | N24: Social media | R24: 23 | S24: =PROPER(CustomerSupport[[#This Row],[Resolution]]) | T24: =TRIM(CustomerSupport[[#This Row],[Customer Name]]) -> Stephanie Nelson DVM | U24: =MONTH(CustomerSupport[[#This Row],[Date of Purchase]]) -> 2 | V24: =TEXT('Working data'!G24,"mmmm") -> February | W24: =YEAR(CustomerSupport[[#This Row],[Date of Purchase]]) -> 2020 | X24: =IF(OR(O24="",P24=""),"",(P24-O24)*24)
A25: 24 | B25: Antonio Scott | C25: carlsonmatthew@example.org | D25: 63 | E25: Female | F25: Nintendo Switch Pro Controller | G25: 44414 | H25: Technical issue | I25: Refund request | J25: I'm having an issue with the {product_purchased}. Please assist. I'll take care of those. I've performed a factory reset on my {product_purchased}, hoping it would resolve the problem, but it didn't help. | K25: Pending Customer Response | M25: Low | N25: Social media | O25: 45078.379 | R25: 24 | S25: =PROPER(CustomerSupport[[#This Row],[Resolution]]) | T25: =TRIM(CustomerSupport[[#This Row],[Customer Name]]) -> Antonio Scott | U25: =MONTH(CustomerSupport[[#This Row],[Date of Purchase]]) -> 8 | V25: =TEXT('Working data'!G25,"mmmm") -> August | W25: =YEAR(CustomerSupport[[#This Row],[Date of Purchase]]) -> 2021 | X25: =IF(OR(O25="",P25=""),"",(P25-O25)*24)
A26: 25 | B26: John Cuevas | C26: lbarron@example.org | D26: 19 | E26: Male | F26: Amazon Kindle | G26: 44341 | H26: Product inquiry | I26: Display issue | J26: I'm having an issue with the {product_purchased}. Please assist. {product_purchased} does not represent the price which you received by the day immediately before the shipment date. In many cases, this is the I've noticed a sudden decrease in battery life on my {product_purchased}. It used to last much longer. | K26: Open | M26: Critical | N26: Email | R26: 25 | S26: =PROPER(CustomerSupport[[#This Row],[Resolution]]) | T26: =TRIM(CustomerSupport[[#This Row],[Customer Name]]) -> John Cuevas | U26: =MONTH(CustomerSupport[[#This Row],[Date of Purchase]]) -> 5 | V26: =TEXT('Working data'!G26,"mmmm") -> May | W26: =YEAR(CustomerSupport[[#This Row],[Date of Purchase]]) -> 2021 | X26: =IF(OR(O26="",P26=""),"",(P26-O26)*24)
A27: 26 | B27: Gregory Bautista | C27: johnstonbeth@example.com | D27: 35 | E27: Other | F27: HP Pavilion | G27: 44382 | H27: Product inquiry | I27: Refund request | J27: My {product_purchased} is making strange noises and not functioning properly. I suspect there might be a hardware issue. Can you please help me with this? Thank you, Thank you for posting. It took me a I'm experiencing this issue on multiple devices of the same model, so it seems to be a widespread problem. | K27: Pending Customer Response | M27: Medium | N27: Social media | O27: 45078.793 | R27: 26 | S27: =PROPER(CustomerSupport[[#This Row],[Resolution]]) | T27: =TRIM(CustomerSupport[[#This Row],[Customer Name]]) -> Gregory Bautista | U27: =MONTH(CustomerSupport[[#This Row],[Date of Purchase]]) -> 7 | V27: =TEXT('Working data'!G27,"mmmm") -> July | W27: =YEAR(CustomerSupport[[#This Row],[Date of Purchase]]) -> 2021 | X27: =IF(OR(O27="",P27=""),"",(P27-O27)*24)
A28: 27 | B28: Ryan Sharp | C28: pmercado@example.org | D28: 22 | E28: Other | F28: Lenovo ThinkPad | G28: 43953 | H28: Billing inquiry | I28: Cancellation request | J28: I'm encountering a software bug in the {product_purchased}. Whenever I try to perform a specific action, the application crashes. Are there any updates or fixes available? On Windows Vista, this is not possible. If you are I've performed a factory reset on my {product_purchased}, hoping it would resolve the problem, but it didn't help. | K28: Pending Customer Response | M28: Low | N28: Social media | O28: 45078.835 | R28: 27 | S28: =PROPER(CustomerSupport[[#This Row],[Resolution]]) | T28: =TRIM(CustomerSupport[[#This Row],[Customer Name]]) -> Ryan Sharp | U28: =MONTH(CustomerSupport[[#This Row],[Date of Purchase]]) -> 5 | V28: =TEXT('Working data'!G28,"mmmm") -> May | W28: =YEAR(CustomerSupport[[#This Row],[Date of Purchase]]) -> 2020 | X28: =IF(OR(O28="",P28=""),"",(P28-O28)*24)
A29: 28 | B29: Michael Mcdowell | C29: jeffersonmichael@example.net | D29: 21 | E29: Other | F29: Fitbit Charge | G29: 44116 | H29: Cancellation request | I29: Product setup | J29: I'm having an issue with the {product_purchased}. Please assist. {{product_purchased}} must be a valid email address for your order and are valid for one week in advance. Please make your purchases as quickly as possible The issue I'm facing is intermittent. Sometimes it works fine, but other times it acts up unexpectedly. | K29: Open | M29: High | N29: Phone | R29: 28 | S29: =PROPER(CustomerSupport[[#This Row],[Resolution]]) | T29: =TRIM(CustomerSupport[[#This Row],[Customer Name]]) -> Michael Mcdowell | U29: =MONTH(CustomerSupport[[#This Row],[Date of Purchase]]) -> 10 | V29: =TEXT('Working data'!G29,"mmmm") -> October | W29: =YEAR(CustomerSupport[[#This Row],[Date of Purchase]]) -> 2020 | X29: =IF(OR(O29="",P29=""),"",(P29-O29)*24)
A30: 29 | B30: Christine Wang | C30: garciastacy@example.com | D30: 30 | E30: Other | F30: Fitbit Charge | G30: 43992 | H30: Technical issue | I30: Product recommendation | J30: I'm having an issue with the {product_purchased}. Please assist. Thank you." A statement from the consumer group had been released by Microsoft late on Tuesday afternoon. "The purchase of this product was made using a contract with I'm using the original charger that came with my {product_purchased}, but it's not charging properly. | K30: Closed | L30: Soldier we such inside. | M30: Critical | N30: Phone | O30: 45077.97 | P30: 45078.252 | Q30: 5 | R30: 29 | S30: =PROPER(CustomerSupport[[#This Row],[Resolution]]) -> Soldier We Such Inside. | T30: =TRIM(CustomerSupport[[#This Row],[Customer Name]]) -> Christine Wang | U30: =MONTH(CustomerSupport[[#This Row],[Date of Purchase]]) -> 6 | V30: =TEXT('Working data'!G30,"mmmm") -> June | W30: =YEAR(CustomerSupport[[#This Row],[Date of Purchase]]) -> 2020 | X30: =IF(OR(O30="",P30=""),"",(P30-O30)*24) -> 6.7666667
A31: 30 | B31: Austin George | C31: shericase@example.net | D31: 67 | E31: Male | F31: Xbox | G31: 44191 | H31: Cancellation request | I31: Cancellation request | J31: I'm having an issue with the {product_purchased}. Please assist. It's not possible to remove the missing content. I've already contacted customer support multiple times, but the issue remains unresolved. | K31: Closed | L31: Firm sort voice above which site arrive. | M31: Medium | N31: Phone | O31: 45078.038 | P31: 45078.766 | Q31: 1 | R31: 30 | S31: =PROPER(CustomerSupport[[#This Row],[Resolution]]) -> Firm Sort Voice Above Which Site Arrive. | T31: =TRIM(CustomerSupport[[#This Row],[Customer Name]]) -> Austin George | U31: =MONTH(CustomerSupport[[#This Row],[Date of Purchase]]) -> 12 | V31: =TEXT('Working data'!G31,"mmmm") -> December | W31: =YEAR(CustomerSupport[[#This Row],[Date of Purchase]]) -> 2020 | X31: =IF(OR(O31="",P31=""),"",(P31-O31)*24) -> 17.483333
A32: 31 | B32: Wendy Roberts | C32: jessicahenderson@example.net | D32: 22 | E32: Other | F32: Adobe Photoshop | G32: 44224 | H32: Billing inquiry | I32: Product setup | J32: I'm having an issue with the {product_purchased}. Please assist. I'm using a brand new product. What a strange situation. I've just purchased a brand new one. What to do? I've noticed that the issue occurs consistently when I use a specific feature or application on my {product_purchased}. | K32: Open | M32: Low | N32: Email | R32: 31 | S32: =PROPER(CustomerSupport[[#This Row],[Resolution]]) | T32: =TRIM(CustomerSupport[[#This Row],[Customer Name]]) -> Wendy Roberts | U32: =MONTH(CustomerSupport[[#This Row],[Date of Purchase]]) -> 1 | V32: =TEXT('Working data'!G32,"mmmm") -> January | W32: =YEAR(CustomerSupport[[#This Row],[Date of Purchase]]) -> 2021 | X32: =IF(OR(O32="",P32=""),"",(P32-O32)*24)
A33: 32 | B33: Robert Wilson | C33: zstewart@example.org | D33: 60 | E33: Male | F33: GoPro Action Camera | G33: 44550 | H33: Technical issue | I33: Product compatibility | J33: I'm having an issue with the {product_purchased}. Please assist. The seller has sold the item for $29.89. When we receive your replacement, we will exchange the item for a full refund or exchange immediately upon I've already contacted customer support multiple times, but the issue remains unresolved. | K33: Closed | L33: Certain myself month past tree benefit. | M33: Medium | N33: Social media | O33: 45078.279 | P33: 45078.303 | Q33: 3 | R33: 32 | S33: =PROPER(CustomerSupport[[#This Row],[Resolution]]) -> Certain Myself Month Past Tree Benefit. | T33: =TRIM(CustomerSupport[[#This Row],[Customer Name]]) -> Robert Wilson | U33: =MONTH(CustomerSupport[[#This Row],[Date of Purchase]]) -> 12 | V33: =TEXT('Working data'!G33,"mmmm") -> December | W33: =YEAR(CustomerSupport[[#This Row],[Date of Purchase]]) -> 2021 | X33: =IF(OR(O33="",P33=""),"",(P33-O33)*24) -> 0.56666667
A34: 33 | B34: Christina Gray | C34: greenkeith@example.net | D34: 36 | E34: Female | F34: Fitbit Charge | G34: 44537 | H34: Billing inquiry | I34: Product recommendation | J34: I've noticed a software bug in the {product_purchased} app. It's causing data loss and unexpected errors. How can I resolve this issue? I need assistance as soon as possible because it's affecting my work and productivity. | K34: Pending Customer Response | M34: Medium | N34: Chat | O34: 45078.817 | R34: 33 | S34: =PROPER(CustomerSupport[[#This Row],[Resolution]]) | T34: =TRIM(CustomerSupport[[#This Row],[Customer Name]]) -> Christina Gray | U34: =MONTH(CustomerSupport[[#This Row],[Date of Purchase]]) -> 12 | V34: =TEXT('Working data'!G34,"mmmm") -> December | W34: =YEAR(CustomerSupport[[#This Row],[Date of Purchase]]) -> 2021 | X34: =IF(OR(O34="",P34=""),"",(P34-O34)*24)
A35: 34 | B35: Timothy Lyons | C35: darlenelee@example.org | D35: 50 | E35: Male | F35: Autodesk AutoCAD | G35: 44539 | H35: Refund request | I35: Hardware issue | J35: I'm having an issue with the {product_purchased}. Please assist. We hope that every vendor takes the time it takes in to do the following: "Remove the product from your account - notify consumers, call them, make their I'm concerned about the security of my {product_purchased} and would like to ensure that my data is safe. | K35: Closed | L35: However financial development significant camera job every. | M35: Critical | N35: Social media | O35: 45078.084 | P35: 45078.768 | Q35: 5 | R35: 34 | S35: =PROPER(CustomerSupport[[#This Row],[Resolution]]) -> However Financial Development Significant Camera Job Every. | T35: =TRIM(CustomerSupport[[#This Row],[Customer Name]]) -> Timothy Lyons | U35: =MONTH(CustomerSupport[[#This Row],[Date of Purchase]]) -> 12 | V35: =TEXT('Working data'!G35,"mmmm") -> December | W35: =YEAR(CustomerSupport[[#This Row],[Date of Purchase]]) -> 2021 | X35: =IF(OR(O35="",P35=""),"",(P35-O35)*24) -> 16.4
A36: 35 | B36: Stacy Jones | C36: fernandezmark@example.org | D36: 27 | E36: Male | F36: Microsoft Xbox Controller | G36: 44295 | H36: Refund request | I36: Installation support | J36: I'm having an issue with the {product_purchased}. Please assist. 3-3 We are in, the first day, at the {product_purchased}. Please assist. 3-2 Please assist us I've recently updated the firmware of my {product_purchased}, and the issue started happening afterward. Could it be related to the update? | K36: Pending Customer Response | M36: Low | N36: Chat | O36: 45078.868 | R36: 35 | S36: =PROPER(CustomerSupport[[#This Row],[Resolution]]) | T36: =TRIM(CustomerSupport[[#This Row],[Customer Name]]) -> Stacy Jones | U36: =MONTH(CustomerSupport[[#This Row],[Date of Purchase]]) -> 4 | V36: =TEXT('Working data'!G36,"mmmm") -> April | W36: =YEAR(CustomerSupport[[#This Row],[Date of Purchase]]) -> 2021 | X36: =IF(OR(O36="",P36=""),"",(P36-O36)*24)
A37: 36 | B37: Joann King | C37: jessica10@example.org | D37: 24 | E37: Other | F37: GoPro Hero | G37: 44117 | H37: Cancellation request | I37: Product recommendation | J37: I've recently set up my {product_purchased}, but it fails to connect to any available networks. What steps should I take to troubleshoot this issue? If you know the answer, please let me know. Do I I've noticed a sudden decrease in battery life on my {product_purchased}. It used to last much longer. | K37: Closed | L37: Reach paper ability effort learn. | M37: High | N37: Chat | O37: 45078.331 | P37: 45078.01 | Q37: 1 | R37: 36 | S37: =PROPER(CustomerSupport[[#This Row],[Resolution]]) -> Reach Paper Ability Effort Learn. | T37: =TRIM(CustomerSupport[[#This Row],[Customer Name]]) -> Joann King | U37: =MONTH(CustomerSupport[[#This Row],[Date of Purchase]]) -> 10 | V37: =TEXT('Working data'!G37,"mmmm") -> October | W37: =YEAR(CustomerSupport[[#This Row],[Date of Purchase]]) -> 2020 | X37: =IF(OR(O37="",P37=""),"",(P37-O37)*24) -> -7.7
A38: 37 | B38: Ruben Henry | C38: katherinehoward@example.net | D38: 65 | E38: Female | F38: Canon EOS | G38: 43904 | H38: Refund request | I38: Hardware issue | J38: I'm having an issue with the {product_purchased}. Please assist. I have to ask for support from you, the customers, before the item's arrival and I can't do that. In the short term, will you pay me I've followed the troubleshooting steps mentioned in the user manual, but the issue persists. | K38: Pending Customer Response | M38: Medium | N38: Email | O38: 45078.661 | R38: 37 | S38: =PROPER(CustomerSupport[[#This Row],[Resolution]]) | T38: =TRIM(CustomerSupport[[#This Row],[Customer Name]]) -> Ruben Henry | U38: =MONTH(CustomerSupport[[#This Row],[Date of Purchase]]) -> 3 | V38: =TEXT('Working data'!G38,"mmmm") -> March | W38: =YEAR(CustomerSupport[[#This Row],[Date of Purchase]]) -> 2020 | X38: =IF(OR(O38="",P38=""),"",(P38-O38)*24)
A39: 38 | B39: Morgan Wagner | C39: elizabethlamb@example.com | D39: 39 | E39: Female | F39: Amazon Kindle | G39: 44076 | H39: Product inquiry | I39: Product compatibility | J39: I've forgotten my password for my {product_purchased} account, and the password reset option is not working. How can I recover my account? I can reset my password by entering the following: My password still valid: password is expired I've recently updated the firmware of my {product_purchased}, and the issue started happening afterward. Could it be related to the update? | K39: Open | M39: Medium | N39: Chat | R39: 38 | S39: =PROPER(CustomerSupport[[#This Row],[Resolution]]) | T39: =TRIM(CustomerSupport[[#This Row],[Customer Name]]) -> Morgan Wagner | U39: =MONTH(CustomerSupport[[#This Row],[Date of Purchase]]) -> 9 | V39: =TEXT('Working data'!G39,"mmmm") -> September | W39: =YEAR(CustomerSupport[[#This Row],[Date of Purchase]]) -> 2020 | X39: =IF(OR(O39="",P39=""),"",(P39-O39)*24)
A40: 39 | B40: Kevin Ingram | C40: victor62@example.net | D40: 19 | E40: Male | F40: Google Pixel | G40: 44449 | H40: Technical issue | I40: Account access | J40: I'm having an issue with the {product_purchased}. Please assist. 1. Do I need to purchase a refund? There is a way to purchase a refund from ZEROHITS, but there's not a I'm unable to find the option to perform the desired action in the {product_purchased}. Could you please guide me through the steps? | K40: Closed | L40: North second between this cell opportunity movement. | M40: Critical | N40: Phone | O40: 45078.782 | P40: 45077.912 | Q40: 3 | R40: 39 | S40: =PROPER(CustomerSupport[[#This Row],[Resolution]]) -> North Second Between This Cell Opportunity Movement. | T40: =TRIM(CustomerSupport[[#This Row],[Customer Name]]) -> Kevin Ingram | U40: =MONTH(CustomerSupport[[#This Row],[Date of Purchase]]) -> 9 | V40: =TEXT('Working data'!G40,"mmmm") -> September | W40: =YEAR(CustomerSupport[[#This Row],[Date of Purchase]]) -> 2021 | X40: =IF(OR(O40="",P40=""),"",(P40-O40)*24) -> -20.866667
A41: 40 | B41: Michael Oneal | C41: stevenburns@example.net | D41: 33 | E41: Other | F41: Amazon Echo | G41: 44491 | H41: Product inquiry | I41: Account access | J41: I'm having an issue with the {product_purchased}. Please assist. I have a new account in the system and a new user. I'm having this issue Error: [System.CollectedMessage.ThrowBack I'm concerned about the security of my {product_purchased} and would like to ensure that my data is safe. | K41: Pending Customer Response | M41: Medium | N41: Social media | O41: 45077.93 | R41: 40 | S41: =PROPER(CustomerSupport[[#This Row],[Resolution]]) | T41: =TRIM(CustomerSupport[[#This Row],[Customer Name]]) -> Michael Oneal | U41: =MONTH(CustomerSupport[[#This Row],[Date of Purchase]]) -> 10 | V41: =TEXT('Working data'!G41,"mmmm") -> October | W41: =YEAR(CustomerSupport[[#This Row],[Date of Purchase]]) -> 2021 | X41: =IF(OR(O41="",P41=""),"",(P41-O41)*24)
A42: 41 | B42: Casey Tran | C42: shawn54@example.net | D42: 19 | E42: Female | F42: PlayStation | G42: 44234 | H42: Product inquiry | I42: Installation support | J42: I've recently set up my {product_purchased}, but it fails to connect to any available networks. What steps should I take to troubleshoot this issue? The next step is to resolve this issue if the user is not I've noticed that the issue occurs consistently when I use a specific feature or application on my {product_purchased}. | K42: Pending Customer Response | M42: Low | N42: Phone | O42: 45078.383 | R42: 41 | S42: =PROPER(CustomerSupport[[#This Row],[Resolution]]) | T42: =TRIM(CustomerSupport[[#This Row],[Customer Name]]) -> Casey Tran | U42: =MONTH(CustomerSupport[[#This Row],[Date of Purchase]]) -> 2 | V42: =TEXT('Working data'!G42,"mmmm") -> February | W42: =YEAR(CustomerSupport[[#This Row],[Date of Purchase]]) -> 2021 | X42: =IF(OR(O42="",P42=""),"",(P42-O42)*24)
A43: 42 | B43: Katie Mitchell | C43: sheila78@example.org | D43: 35 | E43: Male | F43: Dell XPS | G43: 44356 | H43: Billing inquiry | I43: Product compatibility | J43: I'm facing a problem with my {product_purchased}. The {product_purchased} is not turning on. It was working fine until yesterday, but now it doesn't respond. If I'd just switched to a The issue I'm facing is intermittent. Sometimes it works fine, but other times it acts up unexpectedly. | K43: Closed | L43: Start book field officer seem make. | M43: Critical | N43: Chat | O43: 45078.851 | P43: 45078.614 | Q43: 3 | R43: 42 | S43: =PROPER(CustomerSupport[[#This Row],[Resolution]]) -> Start Book Field Officer Seem Make. | T43: =TRIM(CustomerSupport[[#This Row],[Customer Name]]) -> Katie Mitchell | U43: =MONTH(CustomerSupport[[#This Row],[Date of Purchase]]) -> 6 | V43: =TEXT('Working data'!G43,"mmmm") -> June | W43: =YEAR(CustomerSupport[[#This Row],[Date of Purchase]]) -> 2021 | X43: =IF(OR(O43="",P43=""),"",(P43-O43)*24) -> -5.7
A44: 43 | B44: Justin Giles | C44: woodmargaret@example.org | D44: 22 | E44: Male | F44: Samsung Galaxy | G44: 44114 | H44: Product inquiry | I44: Product compatibility | J44: I'm having an issue with the {product_purchased}. Please assist. The product_purchased attribute does not exist on your user's product. This is so that you can configure the {product_purchased} I need assistance as soon as possible because it's affecting my work and productivity. | K44: Pending Customer Response | M44: Medium | N44: Phone | O44: 45078.779 | R44: 43 | S44: =PROPER(CustomerSupport[[#This Row],[Resolution]]) | T44: =TRIM(CustomerSupport[[#This Row],[Customer Name]]) -> Justin Giles | U44: =MONTH(CustomerSupport[[#This Row],[Date of Purchase]]) -> 10 | V44: =TEXT('Working data'!G44,"mmmm") -> October | W44: =YEAR(CustomerSupport[[#This Row],[Date of Purchase]]) -> 2020 | X44: =IF(OR(O44="",P44=""),"",(P44-O44)*24)
A45: 44 | B45: Michael Allison | C45: abowen@example.org | D45: 54 | E45: Female | F45: iPhone | G45: 43846 | H45: Technical issue | I45: Hardware issue | J45: I'm having an issue with the {product_purchased}. Please assist. Thank you." The issue occurred after Amazon started a tool to deal with a problem like this (see page 36 of the FAQ): "The product is not I've recently updated the firmware of my {product_purchased}, and the issue started happening afterward. Could it be related to the update? | K45: Open | M45: Low | N45: Email | R45: 44 | S45: =PROPER(CustomerSupport[[#This Row],[Resolution]]) | T45: =TRIM(CustomerSupport[[#This Row],[Customer Name]]) -> Michael Allison | U45: =MONTH(CustomerSupport[[#This Row],[Date of Purchase]]) -> 1 | V45: =TEXT('Working data'!G45,"mmmm") -> January | W45: =YEAR(CustomerSupport[[#This Row],[Date of Purchase]]) -> 2020 | X45: =IF(OR(O45="",P45=""),"",(P45-O45)*24)
A46: 45 | B46: Donald Gibbs | C46: laura33@example.org | D46: 34 | E46: Other | F46: HP Pavilion | G46: 44464 | H46: Refund request | I46: Product compatibility | J46: I'm having an issue with the {product_purchased}. Please assist. I wanted a picture for my 3DS, but I already bought a lot of items, so I found an online cart: "Fountain of Dreams Collection I'm unable to find the option to perform the desired action in the {product_purchased}. Could you please guide me through the steps? | K46: Closed | L46: Over read region lawyer much speech control. | M46: Critical | N46: Email | O46: 45078.249 | P46: 45078.139 | Q46: 2 | R46: 45 | S46: =PROPER(CustomerSupport[[#This Row],[Resolution]]) -> Over Read Region Lawyer Much Speech Control. | T46: =TRIM(CustomerSupport[[#This Row],[Customer Name]]) -> Donald Gibbs | U46: =MONTH(CustomerSupport[[#This Row],[Date of Purchase]]) -> 9 | V46: =TEXT('Working data'!G46,"mmmm") -> September | W46: =YEAR(CustomerSupport[[#This Row],[Date of Purchase]]) -> 2021 | X46: =IF(OR(O46="",P46=""),"",(P46-O46)*24) -> -2.65
A47: 46 | B47: Timothy Sutton | C47: david40@example.org | D47: 65 | E47: Female | F47: LG Smart TV | G47: 44228 | H47: Product inquiry | I47: Cancellation request | J47: I'm having an issue with the {product_purchased}. Please assist. Thanks". "As a result I'm having an issue with the 1.0 patch. Please assist." "All I'm asking is to update I'm concerned about the security of my {product_purchased} and would like to ensure that my data is safe. | K47: Open | M47: Low | N47: Chat | R47: 46 | S47: =PROPER(CustomerSupport[[#This Row],[Resolution]]) | T47: =TRIM(CustomerSupport[[#This Row],[Customer Name]]) -> Timothy Sutton | U47: =MONTH(CustomerSupport[[#This Row],[Date of Purchase]]) -> 2 | V47: =TEXT('Working data'!G47,"mmmm") -> February | W47: =YEAR(CustomerSupport[[#This Row],[Date of Purchase]]) -> 2021 | X47: =IF(OR(O47="",P47=""),"",(P47-O47)*24)
A48: 47 | B48: Cassandra Richards | C48: abigail06@example.com | D48: 50 | E48: Female | F48: Nintendo Switch Pro Controller | G48: 44119 | H48: Refund request | I48: Network problem | J48: I'm having an issue with the {product_purchased}. Please assist. We have not yet provided an address or a name for this product. If this website does not exist, please contact us with this information and we will provide it. I need assistance as soon as possible because it's affecting my work and productivity. | K48: Closed | L48: Audience food pretty cut. | M48: High | N48: Phone | O48: 45078.155 | P48: 45078.392 | Q48: 1 | R48: 47 | S48: =PROPER(CustomerSupport[[#This Row],[Resolution]]) -> Audience Food Pretty Cut. | T48: =TRIM(CustomerSupport[[#This Row],[Customer Name]]) -> Cassandra Richards | U48: =MONTH(CustomerSupport[[#This Row],[Date of Purchase]]) -> 10 | V48: =TEXT('Working data'!G48,"mmmm") -> October | W48: =YEAR(CustomerSupport[[#This Row],[Date of Purchase]]) -> 2020 | X48: =IF(OR(O48="",P48=""),"",(P48-O48)*24) -> 5.6833333
A49: 48 | B49: Kristen Perry | C49: bevans@example.org | D49: 27 | E49: Female | F49: GoPro Hero | G49: 44041 | H49: Technical issue | I49: Software bug | J49: I'm having an issue with the {product_purchased}. Please assist. This product is not found on, and should NOT come from, this site. Not sure about what this product covers? Product Description I'm experiencing this issue on multiple devices of the same model, so it seems to be a widespread problem. | K49: Closed | L49: Late center interview that. | M49: Medium | N49: Social media | O49: 45078.303 | P49: 45078.25 | Q49: 1 | R49: 48 | S49: =PROPER(CustomerSupport[[#This Row],[Resolution]]) -> Late Center Interview That. | T49: =TRIM(CustomerSupport[[#This Row],[Customer Name]]) -> Kristen Perry | U49: =MONTH(CustomerSupport[[#This Row],[Date of Purchase]]) -> 7 | V49: =TEXT('Working data'!G49,"mmmm") -> July | W49: =YEAR(CustomerSupport[[#This Row],[Date of Purchase]]) -> 2020 | X49: =IF(OR(O49="",P49=""),"",(P49-O49)*24) -> -1.2833333
A50: 49 | B50: Noah Mcknight | C50: juliepowers@example.org | D50: 32 | E50: Other | F50: LG OLED | G50: 44242 | H50: Cancellation request | I50: Network problem | J50: I'm having an issue with the {product_purchased}. Please assist. Please. Don't. Don't see my issue? Please contact me. I'm unable to find the option to perform the desired action in the {product_purchased}. Could you please guide me through the steps? | K50: Open | M50: High | N50: Chat | R50: 49 | S50: =PROPER(CustomerSupport[[#This Row],[Resolution]]) | T50: =TRIM(CustomerSupport[[#This Row],[Customer Name]]) -> Noah Mcknight | U50: =MONTH(CustomerSupport[[#This Row],[Date of Purchase]]) -> 2 | V50: =TEXT('Working data'!G50,"mmmm") -> February | W50: =YEAR(CustomerSupport[[#This Row],[Date of Purchase]]) -> 2021 | X50: =IF(OR(O50="",P50=""),"",(P50-O50)*24)
A51: 50 | B51: Katie Johnson | C51: thomas46@example.net | D51: 44 | E51: Male | F51: Microsoft Office | G51: 44101 | H51: Technical issue | I51: Display issue | J51: I'm having an issue with the {product_purchased}. Please assist. If you've received a refund, please contact Customer Service. Otherwise, please call us at 303.938.2837. I'm having an issue with the I'm concerned about the security of my {product_purchased} and would like to ensure that my data is safe. | K51: Open | M51: Medium | N51: Chat | R51: 50 | S51: =PROPER(CustomerSupport[[#This Row],[Resolution]]) | T51: =TRIM(CustomerSupport[[#This Row],[Customer Name]]) -> Katie Johnson | U51: =MONTH(CustomerSupport[[#This Row],[Date of Purchase]]) -> 9 | V51: =TEXT('Working data'!G51,"mmmm") -> September | W51: =YEAR(CustomerSupport[[#This Row],[Date of Purchase]]) -> 2020 | X51: =IF(OR(O51="",P51=""),"",(P51-O51)*24)
A52: 51 | B52: Kayla Dunn | C52: ramirezphilip@example.net | D52: 66 | E52: Male | F52: Sony Xperia | G52: 44187 | H52: Refund request | I52: Software bug | J52: I'm encountering a software bug in the {product_purchased}. Whenever I try to perform a specific action, the application crashes. Are there any updates or fixes available? There are several packages that run in memory by default. These I'm experiencing this issue on multiple devices of the same model, so it seems to be a widespread problem. | K52: Open | M52: Medium | N52: Chat | R52: 51 | S52: =PROPER(CustomerSupport[[#This Row],[Resolution]]) | T52: =TRIM(CustomerSupport[[#This Row],[Customer Name]]) -> Kayla Dunn | U52: =MONTH(CustomerSupport[[#This Row],[Date of Purchase]]) -> 12 | V52: =TEXT('Working data'!G52,"mmmm") -> December | W52: =YEAR(CustomerSupport[[#This Row],[Date of Purchase]]) -> 2020 | X52: =IF(OR(O52="",P52=""),"",(P52-O52)*24)
A53: 52 | B53: Tracy White | C53: wvargas@example.com | D53: 64 | E53: Male | F53: LG Smart TV | G53: 44155 | H53: Refund request | I53: Software bug | J53: I've recently set up my {product_purchased}, but it fails to connect to any available networks. What steps should I take to troubleshoot this issue?.......................................................1. Visit https://forum.ejconop I've reviewed the troubleshooting steps on the official support website, but they didn't resolve the problem. | K53: Closed | L53: Might Mrs often stuff. | M53: Medium | N53: Chat | O53: 45078.682 | P53: 45078.439 | Q53: 3 | R53: 52 | S53: =PROPER(CustomerSupport[[#This Row],[Resolution]]) -> Might Mrs Often Stuff. | T53: =TRIM(CustomerSupport[[#This Row],[Customer Name]]) -> Tracy White | U53: =MONTH(CustomerSupport[[#This Row],[Date of Purchase]]) -> 11 | V53: =TEXT('Working data'!G53,"mmmm") -> November | W53: =YEAR(CustomerSupport[[#This Row],[Date of Purchase]]) -> 2020 | X53: =IF(OR(O53="",P53=""),"",(P53-O53)*24) -> -5.8333333
A54: 53 | B54: Christian Graves | C54: hgriffin@example.org | D54: 54 | E54: Male | F54: Nest Thermostat | G54: 44479 | H54: Refund request | I54: Network problem | J54: I'm having an issue with the {product_purchased}. Please assist. Please. Please. I need assistance as soon as possible because it's affecting my work and productivity. | K54: Closed | L54: More left involve agree station billion would. | M54: High | N54: Social media | O54: 45078.08 | P54: 45078.875 | Q54: 3 | R54: 53 | S54: =PROPER(CustomerSupport[[#This Row],[Resolution]]) -> More Left Involve Agree Station Billion Would. | T54: =TRIM(CustomerSupport[[#This Row],[Customer Name]]) -> Christian Graves | U54: =MONTH(CustomerSupport[[#This Row],[Date of Purchase]]) -> 10 | V54: =TEXT('Working data'!G54,"mmmm") -> October | W54: =YEAR(CustomerSupport[[#This Row],[Date of Purchase]]) -> 2021 | X54: =IF(OR(O54="",P54=""),"",(P54-O54)*24) -> 19.083333
A55: 54 | B55: Casey Reed | C55: sabrina61@example.org | D55: 37 | E55: Male | F55: HP Pavilion | G55: 44424 | H55: Cancellation request | I55: Delivery problem | J55: I'm having an issue with the {product_purchased}. Please assist. If it's not working I can't help you. I've performed a factory reset on my {product_purchased}, hoping it would resolve the problem, but it didn't help. | K55: Closed | L55: Even two pay expect. | M55: Low | N55: Chat | O55: 45078.028 | P55: 45078.435 | Q55: 4 | R55: 54 | S55: =PROPER(CustomerSupport[[#This Row],[Resolution]]) -> Even Two Pay Expect. | T55: =TRIM(CustomerSupport[[#This Row],[Customer Name]]) -> Casey Reed | U55: =MONTH(CustomerSupport[[#This Row],[Date of Purchase]]) -> 8 | V55: =TEXT('Working data'!G55,"mmmm") -> August | W55: =YEAR(CustomerSupport[[#This Row],[Date of Purchase]]) -> 2021 | X55: =IF(OR(O55="",P55=""),"",(P55-O55)*24) -> 9.7666667
A56: 55 | B56: Carrie Ayers | C56: natasha18@example.com | D56: 68 | E56: Female | F56: Microsoft Xbox Controller | G56: 44483 | H56: Technical issue | I56: Network problem | J56: I've noticed a software bug in the {product_purchased} app. It's causing data loss and unexpected errors. How can I resolve this issue? For those who live in the U.S., you can use the {product_ I'm unable to find the option to perform the desired action in the {product_purchased}. Could you please guide me through the steps? | K56: Pending Customer Response | M56: Low | N56: Chat | O56: 45078.31 | R56: 55 | S56: =PROPER(CustomerSupport[[#This Row],[Resolution]]) | T56: =TRIM(CustomerSupport[[#This Row],[Customer Name]]) -> Carrie Ayers | U56: =MONTH(CustomerSupport[[#This Row],[Date of Purchase]]) -> 10 | V56: =TEXT('Working data'!G56,"mmmm") -> October | W56: =YEAR(CustomerSupport[[#This Row],[Date of Purchase]]) -> 2021 | X56: =IF(OR(O56="",P56=""),"",(P56-O56)*24)
A57: 56 | B57: Sarah Cole | C57: williamscynthia@example.org | D57: 50 | E57: Female | F57: Nintendo Switch Pro Controller | G57: 44519 | H57: Cancellation request | I57: Software bug | J57: I'm having an issue with the {product_purchased}. Please assist. The requested address will be returned within 3 â€“ 9 business days. Please do not hesitate to contact us using the appropriate form. (9 weeks from purchase time I'm unable to find the option to perform the desired action in the {product_purchased}. Could you please guide me through the steps? | K57: Pending Customer Response | M57: Critical | N57: Chat | O57: 45078.469 | R57: 56 | S57: =PROPER(CustomerSupport[[#This Row],[Resolution]]) | T57: =TRIM(CustomerSupport[[#This Row],[Customer Name]]) -> Sarah Cole | U57: =MONTH(CustomerSupport[[#This Row],[Date of Purchase]]) -> 11 | V57: =TEXT('Working data'!G57,"mmmm") -> November | W57: =YEAR(CustomerSupport[[#This Row],[Date of Purchase]]) -> 2021 | X57: =IF(OR(O57="",P57=""),"",(P57-O57)*24)
A58: 57 | B58: Alison Ford | C58: mcgeebrandon@example.org | D58: 69 | E58: Male | F58: Autodesk AutoCAD | G58: 44552 | H58: Technical issue | I58: Software bug | J58: I'm having an issue with the {product_purchased}. Please assist. I've noticed that the issue occurs consistently when I use a specific feature or application on my {product_purchased}. | K58: Pending Customer Response | M58: Medium | N58: Social media | O58: 45078.44 | R58: 57 | S58: =PROPER(CustomerSupport[[#This Row],[Resolution]]) | T58: =TRIM(CustomerSupport[[#This Row],[Customer Name]]) -> Alison Ford | U58: =MONTH(CustomerSupport[[#This Row],[Date of Purchase]]) -> 12 | V58: =TEXT('Working data'!G58,"mmmm") -> December | W58: =YEAR(CustomerSupport[[#This Row],[Date of Purchase]]) -> 2021 | X58: =IF(OR(O58="",P58=""),"",(P58-O58)*24)
A59: 58 | B59: Lori Young | C59: pthomas@example.org | D59: 47 | E59: Other | F59: GoPro Action Camera | G59: 44040 | H59: Refund request | I59: Peripheral compatibility | J59: I'm having an issue with the {product_purchased}. Please assist. Thank you! This product was added to your friend's shopping cart at your friend's favorite store. Sorry, your account is not loaded. I've followed the troubleshooting steps mentioned in the user manual, but the issue persists. | K59: Open | M59: Critical | N59: Email | R59: 58 | S59: =PROPER(CustomerSupport[[#This Row],[Resolution]]) | T59: =TRIM(CustomerSupport[[#This Row],[Customer Name]]) -> Lori Young | U59: =MONTH(CustomerSupport[[#This Row],[Date of Purchase]]) -> 7 | V59: =TEXT('Working data'!G59,"mmmm") -> July | W59: =YEAR(CustomerSupport[[#This Row],[Date of Purchase]]) -> 2020 | X59: =IF(OR(O59="",P59=""),"",(P59-O59)*24)
A60: 59 | B60: Kimberly Mack | C60: lwilliamson@example.net | D60: 27 | E60: Male | F60: Autodesk AutoCAD | G60: 44043 | H60: Technical issue | I60: Product recommendation | J60: I've forgotten my password for my {product_purchased} account, and the password reset option is not working. How can I recover my account? What happens when you lose all of your money without a credit card? The issue I'm facing is intermittent. Sometimes it works fine, but other times it acts up unexpectedly. | K60: Closed | L60: During base sure measure teach time large. | M60: Medium | N60: Phone | O60: 45078.498 | P60: 45078.199 | Q60: 5 | R60: 59 | S60: =PROPER(CustomerSupport[[#This Row],[Resolution]]) -> During Base Sure Measure Teach Time Large. | T60: =TRIM(CustomerSupport[[#This Row],[Customer Name]]) -> Kimberly Mack | U60: =MONTH(CustomerSupport[[#This Row],[Date of Purchase]]) -> 7 | V60: =TEXT('Working data'!G60,"mmmm") -> July | W60: =YEAR(CustomerSupport[[#This Row],[Date of Purchase]]) -> 2020 | X60: =IF(OR(O60="",P60=""),"",(P60-O60)*24) -> -7.1833333
A61: 60 | B61: Samuel Schroeder | C61: andrew28@example.org | D61: 40 | E61: Other | F61: Apple AirPods | G61: 44444 | H61: Product inquiry | I61: Cancellation request | J61: I'm having an issue with the {product_purchased}. Please assist. Also note: Your information gets deleted every time an article is sent to a website you've never viewed. {Product_id} is a unique identifier in I'm not sure if this issue is specific to my device or if others have reported similar problems. | K61: Closed | L61: Reveal long fish care value direction TV. | M61: Medium | N61: Chat | O61: 45078.827 | P61: 45078.027 | Q61: 3 | R61: 60 | S61: =PROPER(CustomerSupport[[#This Row],[Resolution]]) -> Reveal Long Fish Care Value Direction Tv. | T61: =TRIM(CustomerSupport[[#This Row],[Customer Name]]) -> Samuel Schroeder | U61: =MONTH(CustomerSupport[[#This Row],[Date of Purchase]]) -> 9 | V61: =TEXT('Working data'!G61,"mmmm") -> September | W61: =YEAR(CustomerSupport[[#This Row],[Date of Purchase]]) -> 2021 | X61: =IF(OR(O61="",P61=""),"",(P61-O61)*24) -> -19.2
A62: 61 | B62: Amanda Burton | C62: hannahstephens@example.com | D62: 40 | E62: Male | F62: Sony 4K HDR TV | G62: 44151 | H62: Cancellation request | I62: Product setup | J62: I'm having an issue with the {product_purchased}. Please assist. It's time for me to update the product list I'm having an issue with the{product_purchased}. Please assist. It's time for I've performed a factory reset on my {product_purchased}, hoping it would resolve the problem, but it didn't help. | K62: Closed | L62: Else personal leg break book nearly. | M62: Medium | N62: Chat | O62: 45078.012 | P62: 45078.497 | Q62: 1 | R62: 61 | S62: =PROPER(CustomerSupport[[#This Row],[Resolution]]) -> Else Personal Leg Break Book Nearly. | T62: =TRIM(CustomerSupport[[#This Row],[Customer Name]]) -> Amanda Burton | U62: =MONTH(CustomerSupport[[#This Row],[Date of Purchase]]) -> 11 | V62: =TEXT('Working data'!G62,"mmmm") -> November | W62: =YEAR(CustomerSupport[[#This Row],[Date of Purchase]]) -> 2020 | X62: =IF(OR(O62="",P62=""),"",(P62-O62)*24) -> 11.616667
A63: 62 | B63: Sarah Williams | C63: akelly@example.net | D63: 41 | E63: Other | F63: Lenovo ThinkPad | G63: 44521 | H63: Product inquiry | I63: Battery life | J63: I'm having an issue with the {product_purchased}. Please assist. I was able to get my $50 bag from the vendor, but the bags I was wearing in the show were covered in stickers and the price for those I've tried different settings and configurations on my {product_purchased}, but the issue persists. | K63: Pending Customer Response | M63: Critical | N63: Social media | O63: 45078.064 | R63: 62 | S63: =PROPER(CustomerSupport[[#This Row],[Resolution]]) | T63: =TRIM(CustomerSupport[[#This Row],[Customer Name]]) -> Sarah Williams | U63: =MONTH(CustomerSupport[[#This Row],[Date of Purchase]]) -> 11 | V63: =TEXT('Working data'!G63,"mmmm") -> November | W63: =YEAR(CustomerSupport[[#This Row],[Date of Purchase]]) -> 2021 | X63: =IF(OR(O63="",P63=""),"",(P63-O63)*24)
A64: 63 | B64: Frank Sherman | C64: floresbryan@example.net | D64: 64 | E64: Female | F64: Xbox | G64: 44177 | H64: Billing inquiry | I64: Payment issue | J64: I'm having an issue with the {product_purchased}. Please assist. } } } function getProductCount () {orters(function ($p ) { // This gets the count for all the items in the The issue I'm facing is intermittent. Sometimes it works fine, but other times it acts up unexpectedly. | K64: Closed | L64: Eye while if exist name receive. | M64: High | N64: Email | O64: 45077.984 | P64: 45078.529 | Q64: 4 | R64: 63 | S64: =PROPER(CustomerSupport[[#This Row],[Resolution]]) -> Eye While If Exist Name Receive. | T64: =TRIM(CustomerSupport[[#This Row],[Customer Name]]) -> Frank Sherman | U64: =MONTH(CustomerSupport[[#This Row],[Date of Purchase]]) -> 12 | V64: =TEXT('Working data'!G64,"mmmm") -> December | W64: =YEAR(CustomerSupport[[#This Row],[Date of Purchase]]) -> 2020 | X64: =IF(OR(O64="",P64=""),"",(P64-O64)*24) -> 13.066667
A65: 64 | B65: Victoria Parker | C65: tiffany87@example.com | D65: 57 | E65: Female | F65: Adobe Photoshop | G65: 43945 | H65: Billing inquiry | I65: Hardware issue | J65: I'm having an issue with the {product_purchased}. Please assist. 4.1.7 Add a custom app icon to the app window. Click App Manager. You'll see a list of all of the new apps ( I've checked the device settings and made sure that everything is configured correctly. | K65: Pending Customer Response | M65: High | N65: Phone | O65: 45078.297 | R65: 64 | S65: =PROPER(CustomerSupport[[#This Row],[Resolution]]) | T65: =TRIM(CustomerSupport[[#This Row],[Customer Name]]) -> Victoria Parker | U65: =MONTH(CustomerSupport[[#This Row],[Date of Purchase]]) -> 4 | V65: =TEXT('Working data'!G65,"mmmm") -> April | W65: =YEAR(CustomerSupport[[#This Row],[Date of Purchase]]) -> 2020 | X65: =IF(OR(O65="",P65=""),"",(P65-O65)*24)
A66: 65 | B66: David Smith | C66: jacob67@example.net | D66: 61 | E66: Male | F66: Microsoft Xbox Controller | G66: 44410 | H66: Technical issue | I66: Product compatibility | J66: I'm facing a problem with my {product_purchased}. The {product_purchased} is not turning on. It was working fine until yesterday, but now it doesn't respond. I'm working around this problem by switching off I've noticed a peculiar error message popping up on my {product_purchased} screen. It says '{error_message}'. What does it mean? | K66: Open | M66: Medium | N66: Phone | R66: 65 | S66: =PROPER(CustomerSupport[[#This Row],[Resolution]]) | T66: =TRIM(CustomerSupport[[#This Row],[Customer Name]]) -> David Smith | U66: =MONTH(CustomerSupport[[#This Row],[Date of Purchase]]) -> 8 | V66: =TEXT('Working data'!G66,"mmmm") -> August | W66: =YEAR(CustomerSupport[[#This Row],[Date of Purchase]]) -> 2021 | X66: =IF(OR(O66="",P66=""),"",(P66-O66)*24)
A67: 66 | B67: Jeffrey Hernandez | C67: perezdana@example.org | D67: 56 | E67: Male | F67: Apple AirPods | G67: 44511 | H67: Technical issue | I67: Battery life | J67: There seems to be a glitch in the {product_purchased} software. It freezes frequently, making it difficult to use. Can you please provide a solution? "I'd love to do this on my own. It's a I've noticed a peculiar error message popping up on my {product_purchased} screen. It says '{error_message}'. What does it mean? | K67: Pending Customer Response | M67: Medium | N67: Phone | O67: 45077.943 | R67: 66 | S67: =PROPER(CustomerSupport[[#This Row],[Resolution]]) | T67: =TRIM(CustomerSupport[[#This Row],[Customer Name]]) -> Jeffrey Hernandez | U67: =MONTH(CustomerSupport[[#This Row],[Date of Purchase]]) -> 11 | V67: =TEXT('Working data'!G67,"mmmm") -> November | W67: =YEAR(CustomerSupport[[#This Row],[Date of Purchase]]) -> 2021 | X67: =IF(OR(O67="",P67=""),"",(P67-O67)*24)
A68: 67 | B68: John Robertson | C68: gillespiegeorge@example.com | D68: 49 | E68: Female | F68: GoPro Hero | G68: 44416 | H68: Billing inquiry | I68: Product compatibility | J68: I've noticed a software bug in the {product_purchased} app. It's causing data loss and unexpected errors. How can I resolve this issue? A good way to resolve this software issue is to use a custom configuration file The issue I'm facing is intermittent. Sometimes it works fine, but other times it acts up unexpectedly. | K68: Closed | L68: Fill young add between morning commercial. | M68: High | N68: Email | O68: 45078.213 | P68: 45078.429 | Q68: 5 | R68: 67 | S68: =PROPER(CustomerSupport[[#This Row],[Resolution]]) -> Fill Young Add Between Morning Commercial. | T68: =TRIM(CustomerSupport[[#This Row],[Customer Name]]) -> John Robertson | U68: =MONTH(CustomerSupport[[#This Row],[Date of Purchase]]) -> 8 | V68: =TEXT('Working data'!G68,"mmmm") -> August | W68: =YEAR(CustomerSupport[[#This Row],[Date of Purchase]]) -> 2021 | X68: =IF(OR(O68="",P68=""),"",(P68-O68)*24) -> 5.1833333
A69: 68 | B69: Ryan Gonzalez | C69: pwilson@example.com | D69: 54 | E69: Male | F69: Microsoft Office | G69: 44374 | H69: Cancellation request | I69: Peripheral compatibility | J69: I've accidentally deleted important data from my {product_purchased}. Is there any way to recover the deleted files? I need them urgently. What can I do to recover them? Product purchases are never recoverable from the database. I'm worried that the issue might be hardware-related and might require repair or replacement. | K69: Pending Customer Response | M69: Low | N69: Phone | O69: 45078.878 | R69: 68 | S69: =PROPER(CustomerSupport[[#This Row],[Resolution]]) | T69: =TRIM(CustomerSupport[[#This Row],[Customer Name]]) -> Ryan Gonzalez | U69: =MONTH(CustomerSupport[[#This Row],[Date of Purchase]]) -> 6 | V69: =TEXT('Working data'!G69,"mmmm") -> June | W69: =YEAR(CustomerSupport[[#This Row],[Date of Purchase]]) -> 2021 | X69: =IF(OR(O69="",P69=""),"",(P69-O69)*24)
A70: 69 | B70: Brianna Scott MD | C70: jbranch@example.net | D70: 51 | E70: Other | F70: Adobe Photoshop | G70: 44233 | H70: Technical issue | I70: Product compatibility | J70: I'm having an issue with the {product_purchased}. Please assist. If your product is purchased with the {product_purchased}, the {product_purchased} will be refunded. 7) Pay it I've performed a factory reset on my {product_purchased}, hoping it would resolve the problem, but it didn't help. | K70: Pending Customer Response | M70: Critical | N70: Chat | O70: 45077.958 | R70: 69 | S70: =PROPER(CustomerSupport[[#This Row],[Resolution]]) | T70: =TRIM(CustomerSupport[[#This Row],[Customer Name]]) -> Brianna Scott MD | U70: =MONTH(CustomerSupport[[#This Row],[Date of Purchase]]) -> 2 | V70: =TEXT('Working data'!G70,"mmmm") -> February | W70: =YEAR(CustomerSupport[[#This Row],[Date of Purchase]]) -> 2021 | X70: =IF(OR(O70="",P70=""),"",(P70-O70)*24)
A71: 70 | B71: Michael Day | C71: william07@example.org | D71: 46 | E71: Female | F71: Canon DSLR Camera | G71: 43874 | H71: Refund request | I71: Refund request | J71: I'm unable to access my {product_purchased} account. It keeps displaying an 'Invalid Credentials' error, even though I'm using the correct login information. How can I regain access to my account? If you don't I'm concerned about the security of my {product_purchased} and would like to ensure that my data is safe. | K71: Closed | L71: Answer story series imagine discover. | M71: High | N71: Chat | O71: 45078.498 | P71: 45077.952 | Q71: 1 | R71: 70 | S71: =PROPER(CustomerSupport[[#This Row],[Resolution]]) -> Answer Story Series Imagine Discover. | T71: =TRIM(CustomerSupport[[#This Row],[Customer Name]]) -> Michael Day | U71: =MONTH(CustomerSupport[[#This Row],[Date of Purchase]]) -> 2 | V71: =TEXT('Working data'!G71,"mmmm") -> February | W71: =YEAR(CustomerSupport[[#This Row],[Date of Purchase]]) -> 2020 | X71: =IF(OR(O71="",P71=""),"",(P71-O71)*24) -> -13.1
A72: 71 | B72: Eileen Kim | C72: gabriel83@example.com | D72: 27 | E72: Male | F72: Google Pixel | G72: 44331 | H72: Cancellation request | I72: Product setup | J72: I've accidentally deleted important data from my {product_purchased}. Is there any way to recover the deleted files? I need them urgently. What about my {search } files? The {product_purchased} is the I'm using the original charger that came with my {product_purchased}, but it's not charging properly. | K72: Pending Customer Response | M72: Medium | N72: Chat | O72: 45077.993 | R72: 71 | S72: =PROPER(CustomerSupport[[#This Row],[Resolution]]) | T72: =TRIM(CustomerSupport[[#This Row],[Customer Name]]) -> Eileen Kim | U72: =MONTH(CustomerSupport[[#This Row],[Date of Purchase]]) -> 5 | V72: =TEXT('Working data'!G72,"mmmm") -> May | W72: =YEAR(CustomerSupport[[#This Row],[Date of Purchase]]) -> 2021 | X72: =IF(OR(O72="",P72=""),"",(P72-O72)*24)
A73: 72 | B73: Joseph Costa | C73: calvarez@example.org | D73: 37 | E73: Other | F73: iPhone | G73: 44100 | H73: Refund request | I73: Delivery problem | J73: I've recently set up my {product_purchased}, but it fails to connect to any available networks. What steps should I take to troubleshoot this issue? I've tried clearing the cache and data for the {product_purchased} app, but the issue persists. | K73: Open | M73: Medium | N73: Social media | R73: 72 | S73: =PROPER(CustomerSupport[[#This Row],[Resolution]]) | T73: =TRIM(CustomerSupport[[#This Row],[Customer Name]]) -> Joseph Costa | U73: =MONTH(CustomerSupport[[#This Row],[Date of Purchase]]) -> 9 | V73: =TEXT('Working data'!G73,"mmmm") -> September | W73: =YEAR(CustomerSupport[[#This Row],[Date of Purchase]]) -> 2020 | X73: =IF(OR(O73="",P73=""),"",(P73-O73)*24)
A74: 73 | B74: Tanya Powell | C74: epatel@example.org | D74: 34 | E74: Female | F74: Dyson Vacuum Cleaner | G74: 44243 | H74: Billing inquiry | I74: Display issue | J74: I'm having an issue with the {product_purchased}. Please assist. When I first noticed {product_purchased} the new price of the book was too high. I've already sent out the refund request, but they will I've checked for software updates, and my {product_purchased} is already running the latest version. | K74: Closed | L74: Executive wear gun child. | M74: Low | N74: Chat | O74: 45078.191 | P74: 45078.137 | Q74: 4 | R74: 73 | S74: =PROPER(CustomerSupport[[#This Row],[Resolution]]) -> Executive Wear Gun Child. | T74: =TRIM(CustomerSupport[[#This Row],[Customer Name]]) -> Tanya Powell | U74: =MONTH(CustomerSupport[[#This Row],[Date of Purchase]]) -> 2 | V74: =TEXT('Working data'!G74,"mmmm") -> February | W74: =YEAR(CustomerSupport[[#This Row],[Date of Purchase]]) -> 2021 | X74: =IF(OR(O74="",P74=""),"",(P74-O74)*24) -> -1.3
A75: 74 | B75: Philip Davis | C75: fbenjamin@example.org | D75: 36 | E75: Other | F75: Fitbit Charge | G75: 44144 | H75: Cancellation request | I75: Payment issue | J75: My {product_purchased} is making strange noises and not functioning properly. I suspect there might be a hardware issue. Can you please help me with this? This is a product that must fit in a box. Please let me I've noticed a peculiar error message popping up on my {product_purchased} screen. It says '{error_message}'. What does it mean? | K75: Closed | L75: Finish common benefit most college. | M75: Critical | N75: Social media | O75: 45078.897 | P75: 45078.1 | Q75: 3 | R75: 74 | S75: =PROPER(CustomerSupport[[#This Row],[Resolution]]) -> Finish Common Benefit Most College. | T75: =TRIM(CustomerSupport[[#This Row],[Customer Name]]) -> Philip Davis | U75: =MONTH(CustomerSupport[[#This Row],[Date of Purchase]]) -> 11 | V75: =TEXT('Working data'!G75,"mmmm") -> November | W75: =YEAR(CustomerSupport[[#This Row],[Date of Purchase]]) -> 2020 | X75: =IF(OR(O75="",P75=""),"",(P75-O75)*24) -> -19.116667
A76: 75 | B76: Vanessa Hayes | C76: donaldroberts@example.net | D76: 31 | E76: Female | F76: Xbox | G76: 44302 | H76: Billing inquiry | I76: Product setup | J76: I'm having an issue with the {product_purchased}. Please assist. Please, take care of such requests. [1] M.V.V. [2] The above-mentioned is made up with specific I've checked the device settings and made sure that everything is configured correctly. | K76: Open | M76: Critical | N76: Email | R76: 75 | S76: =PROPER(CustomerSupport[[#This Row],[Resolution]]) | T76: =TRIM(CustomerSupport[[#This Row],[Customer Name]]) -> Vanessa Hayes | U76: =MONTH(CustomerSupport[[#This Row],[Date of Purchase]]) -> 4 | V76: =TEXT('Working data'!G76,"mmmm") -> April | W76: =YEAR(CustomerSupport[[#This Row],[Date of Purchase]]) -> 2021 | X76: =IF(OR(O76="",P76=""),"",(P76-O76)*24)
A77: 76 | B77: Jennifer Bryan | C77: cooperthomas@example.com | D77: 37 | E77: Other | F77: Roomba Robot Vacuum | G77: 44202 | H77: Product inquiry | I77: Display issue | J77: I'm having an issue with the {product_purchased}. Please assist. 1. It is not allowed to purchase a product from an individual, or for a company in which there are no specific employees or employees, and all products have to I've followed the troubleshooting steps mentioned in the user manual, but the issue persists. | K77: Closed | L77: Somebody east painting tree sell rock level. | M77: Critical | N77: Chat | O77: 45078.613 | P77: 45078.104 | Q77: 1 | R77: 76 | S77: =PROPER(CustomerSupport[[#This Row],[Resolution]]) -> Somebody East Painting Tree Sell Rock Level. | T77: =TRIM(CustomerSupport[[#This Row],[Customer Name]]) -> Jennifer Bryan | U77: =MONTH(CustomerSupport[[#This Row],[Date of Purchase]]) -> 1 | V77: =TEXT('Working data'!G77,"mmmm") -> January | W77: =YEAR(CustomerSupport[[#This Row],[Date of Purchase]]) -> 2021 | X77: =IF(OR(O77="",P77=""),"",(P77-O77)*24) -> -12.216667
A78: 77 | B78: Matthew Scott | C78: brookeross@example.net | D78: 18 | E78: Other | F78: iPhone | G78: 44012 | H78: Cancellation request | I78: Account access | J78: I'm having an issue with the {product_purchased}. Please assist. I've got a customer who has sent me a $25 invoice! I want to know if this will correct this. I just downloaded the demo and I I'm experiencing this issue on multiple devices of the same model, so it seems to be a widespread problem. | K78: Open | M78: Critical | N78: Phone | R78: 77 | S78: =PROPER(CustomerSupport[[#This Row],[Resolution]]) | T78: =TRIM(CustomerSupport[[#This Row],[Customer Name]]) -> Matthew Scott | U78: =MONTH(CustomerSupport[[#This Row],[Date of Purchase]]) -> 6 | V78: =TEXT('Working data'!G78,"mmmm") -> June | W78: =YEAR(CustomerSupport[[#This Row],[Date of Purchase]]) -> 2020 | X78: =IF(OR(O78="",P78=""),"",(P78-O78)*24)
A79: 78 | B79: Alfred Ortiz | C79: nicholsdouglas@example.org | D79: 63 | E79: Female | F79: Fitbit Charge | G79: 44194 | H79: Billing inquiry | I79: Delivery problem | J79: I'm having an issue with the {product_purchased}. Please assist. Product #8 4-8-0-1 The product code on your product. #Product ID : {product_id I've checked the device settings and made sure that everything is configured correctly. | K79: Closed | L79: Huge value apply born. | M79: Low | N79: Email | O79: 45078.803 | P79: 45078.64 | Q79: 5 | R79: 78 | S79: =PROPER(CustomerSupport[[#This Row],[Resolution]]) -> Huge Value Apply Born. | T79: =TRIM(CustomerSupport[[#This Row],[Customer Name]]) -> Alfred Ortiz | U79: =MONTH(CustomerSupport[[#This Row],[Date of Purchase]]) -> 12 | V79: =TEXT('Working data'!G79,"mmmm") -> December | W79: =YEAR(CustomerSupport[[#This Row],[Date of Purchase]]) -> 2020 | X79: =IF(OR(O79="",P79=""),"",(P79-O79)*24) -> -3.9166667
A80: 79 | B80: John Goodman | C80: vgarcia@example.com | D80: 55 | E80: Other | F80: Google Pixel | G80: 44203 | H80: Billing inquiry | I80: Data loss | J80: I'm having an issue with the {product_purchased}. Please assist. Thank you The customer's rating and reviews are important, but they don't have an impact on your credit score For over mogul financial companies who have I've performed a factory reset on my {product_purchased}, hoping it would resolve the problem, but it didn't help. | K80: Pending Customer Response | M80: Medium | N80: Social media | O80: 45078.707 | R80: 79 | S80: =PROPER(CustomerSupport[[#This Row],[Resolution]]) | T80: =TRIM(CustomerSupport[[#This Row],[Customer Name]]) -> John Goodman | U80: =MONTH(CustomerSupport[[#This Row],[Date of Purchase]]) -> 1 | V80: =TEXT('Working data'!G80,"mmmm") -> January | W80: =YEAR(CustomerSupport[[#This Row],[Date of Purchase]]) -> 2021 | X80: =IF(OR(O80="",P80=""),"",(P80-O80)*24)
A81: 80 | B81: Catherine Stephens | C81: hmccann@example.com | D81: 40 | E81: Other | F81: LG Smart TV | G81: 44138 | H81: Technical issue | I81: Software bug | J81: I'm having an issue with the {product_purchased}. Please assist. This is for the best experience and you can't use your phone while waiting for deliveries or when you pick it up. Please help by posting a I've tried using different cables, adapters, or peripherals with my {product_purchased}, but the issue persists. | K81: Pending Customer Response | M81: Critical | N81: Chat | O81: 45078.477 | R81: 80 | S81: =PROPER(CustomerSupport[[#This Row],[Resolution]]) | T81: =TRIM(CustomerSupport[[#This Row],[Customer Name]]) -> Catherine Stephens | U81: =MONTH(CustomerSupport[[#This Row],[Date of Purchase]]) -> 11 | V81: =TEXT('Working data'!G81,"mmmm") -> November | W81: =YEAR(CustomerSupport[[#This Row],[Date of Purchase]]) -> 2020 | X81: =IF(OR(O81="",P81=""),"",(P81-O81)*24)
A82: 81 | B82: Sarah Lee | C82: dclark@example.net | D82: 50 | E82: Other | F82: Microsoft Office | G82: 44277 | H82: Technical issue | I82: Product recommendation | J82: I'm having an issue with the {product_purchased}. Please assist. I'm unable to find the option to perform the desired action in the {product_purchased}. Could you please guide me through the steps? | K82: Pending Customer Response | M82: Critical | N82: Phone | O82: 45078.311 | R82: 81 | S82: =PROPER(CustomerSupport[[#This Row],[Resolution]]) | T82: =TRIM(CustomerSupport[[#This Row],[Customer Name]]) -> Sarah Lee | U82: =MONTH(CustomerSupport[[#This Row],[Date of Purchase]]) -> 3 | V82: =TEXT('Working data'!G82,"mmmm") -> March | W82: =YEAR(CustomerSupport[[#This Row],[Date of Purchase]]) -> 2021 | X82: =IF(OR(O82="",P82=""),"",(P82-O82)*24)
A83: 82 | B83: Kiara Parker | C83: gonzalezlarry@example.org | D83: 29 | E83: Other | F83: Apple AirPods | G83: 44399 | H83: Cancellation request | I83: Cancellation request | J83: I'm encountering a software bug in the {product_purchased}. Whenever I try to perform a specific action, the application crashes. Are there any updates or fixes available? I don't know about any updates to the product. It's hard I'm unable to find the option to perform the desired action in the {product_purchased}. Could you please guide me through the steps? | K83: Pending Customer Response | M83: Medium | N83: Email | O83: 45078.484 | R83: 82 | S83: =PROPER(CustomerSupport[[#This Row],[Resolution]]) | T83: =TRIM(CustomerSupport[[#This Row],[Customer Name]]) -> Kiara Parker | U83: =MONTH(CustomerSupport[[#This Row],[Date of Purchase]]) -> 7 | V83: =TEXT('Working data'!G83,"mmmm") -> July | W83: =YEAR(CustomerSupport[[#This Row],[Date of Purchase]]) -> 2021 | X83: =IF(OR(O83="",P83=""),"",(P83-O83)*24)
A84: 83 | B84: Joshua Miller | C84: kimjesse@example.com | D84: 24 | E84: Male | F84: PlayStation | G84: 44473 | H84: Refund request | I84: Software bug | J84: I'm having an issue with the {product_purchased}. Please assist. <p> A full time customer service representative will arrive soon. <p> If you would like to respond to a message I've tried different settings and configurations on my {product_purchased}, but the issue persists. | K84: Closed | L84: Event see dinner home. | M84: Low | N84: Social media | O84: 45078.236 | P84: 45078.858 | Q84: 1 | R84: 83 | S84: =PROPER(CustomerSupport[[#This Row],[Resolution]]) -> Event See Dinner Home. | T84: =TRIM(CustomerSupport[[#This Row],[Customer Name]]) -> Joshua Miller | U84: =MONTH(CustomerSupport[[#This Row],[Date of Purchase]]) -> 10 | V84: =TEXT('Working data'!G84,"mmmm") -> October | W84: =YEAR(CustomerSupport[[#This Row],[Date of Purchase]]) -> 2021 | X84: =IF(OR(O84="",P84=""),"",(P84-O84)*24) -> 14.916667
A85: 84 | B85: James Jones | C85: dsilva@example.org | D85: 57 | E85: Other | F85: Autodesk AutoCAD | G85: 44419 | H85: Technical issue | I85: Installation support | J85: I'm having an issue with the {product_purchased}. Please assist. Your product may be available on other websites with the same keyword or your brand. Thank you. I've noticed a sudden decrease in battery life on my {product_purchased}. It used to last much longer. | K85: Pending Customer Response | M85: Critical | N85: Phone | O85: 45078.017 | R85: 84 | S85: =PROPER(CustomerSupport[[#This Row],[Resolution]]) | T85: =TRIM(CustomerSupport[[#This Row],[Customer Name]]) -> James Jones | U85: =MONTH(CustomerSupport[[#This Row],[Date of Purchase]]) -> 8 | V85: =TEXT('Working data'!G85,"mmmm") -> August | W85: =YEAR(CustomerSupport[[#This Row],[Date of Purchase]]) -> 2021 | X85: =IF(OR(O85="",P85=""),"",(P85-O85)*24)
A86: 85 | B86: David Taylor | C86: kaylapham@example.com | D86: 67 | E86: Other | F86: Microsoft Surface | G86: 44410 | H86: Technical issue | I86: Hardware issue | J86: I'm facing issues logging into my {product_purchased} account. It says my account is locked. What should I do to unlock it? Please log into your login browser and check to see if the account has been locked. I'm experiencing this issue on multiple devices of the same model, so it seems to be a widespread problem. | K86: Open | M86: Medium | N86: Phone | R86: 85 | S86: =PROPER(CustomerSupport[[#This Row],[Resolution]]) | T86: =TRIM(CustomerSupport[[#This Row],[Customer Name]]) -> David Taylor | U86: =MONTH(CustomerSupport[[#This Row],[Date of Purchase]]) -> 8 | V86: =TEXT('Working data'!G86,"mmmm") -> August | W86: =YEAR(CustomerSupport[[#This Row],[Date of Purchase]]) -> 2021 | X86: =IF(OR(O86="",P86=""),"",(P86-O86)*24)
A87: 86 | B87: Richard Mullen | C87: cschmidt@example.com | D87: 67 | E87: Female | F87: Canon EOS | G87: 44218 | H87: Product inquiry | I87: Peripheral compatibility | J87: I've forgotten my password for my {product_purchased} account, and the password reset option is not working. How can I recover my account? If you have not used login tokens for the previous 12 months, the login token I've reviewed the troubleshooting steps on the official support website, but they didn't resolve the problem. | K87: Open | M87: High | N87: Social media | R87: 86 | S87: =PROPER(CustomerSupport[[#This Row],[Resolution]]) | T87: =TRIM(CustomerSupport[[#This Row],[Customer Name]]) -> Richard Mullen | U87: =MONTH(CustomerSupport[[#This Row],[Date of Purchase]]) -> 1 | V87: =TEXT('Working data'!G87,"mmmm") -> January | W87: =YEAR(CustomerSupport[[#This Row],[Date of Purchase]]) -> 2021 | X87: =IF(OR(O87="",P87=""),"",(P87-O87)*24)
A88: 87 | B88: Danielle Everett | C88: kimberlyhudson@example.com | D88: 46 | E88: Male | F88: Sony PlayStation | G88: 43848 | H88: Technical issue | I88: Product recommendation | J88: I'm having an issue with the {product_purchased}. Please assist. * * * @param {number}_item * * @return {item} @*/if (_ejection_exceeds(_proposal)) I've noticed that the issue occurs consistently when I use a specific feature or application on my {product_purchased}. | K88: Closed | L88: Represent where produce suddenly. | M88: Critical | N88: Phone | O88: 45078.752 | P88: 45078.266 | Q88: 2 | R88: 87 | S88: =PROPER(CustomerSupport[[#This Row],[Resolution]]) -> Represent Where Produce Suddenly. | T88: =TRIM(CustomerSupport[[#This Row],[Customer Name]]) -> Danielle Everett | U88: =MONTH(CustomerSupport[[#This Row],[Date of Purchase]]) -> 1 | V88: =TEXT('Working data'!G88,"mmmm") -> January | W88: =YEAR(CustomerSupport[[#This Row],[Date of Purchase]]) -> 2020 | X88: =IF(OR(O88="",P88=""),"",(P88-O88)*24) -> -11.666667
A89: 88 | B89: Steven Thompson | C89: vaustin@example.org | D89: 55 | E89: Other | F89: Philips Hue Lights | G89: 44084 | H89: Technical issue | I89: Delivery problem | J89: I'm facing a problem with my {product_purchased}. The {product_purchased} is not turning on. It was working fine until yesterday, but now it doesn't respond. I'm using a phone now, I'm unable to find the option to perform the desired action in the {product_purchased}. Could you please guide me through the steps? | K89: Pending Customer Response | M89: High | N89: Social media | O89: 45078.807 | R89: 88 | S89: =PROPER(CustomerSupport[[#This Row],[Resolution]]) | T89: =TRIM(CustomerSupport[[#This Row],[Customer Name]]) -> Steven Thompson | U89: =MONTH(CustomerSupport[[#This Row],[Date of Purchase]]) -> 9 | V89: =TEXT('Working data'!G89,"mmmm") -> September | W89: =YEAR(CustomerSupport[[#This Row],[Date of Purchase]]) -> 2020 | X89: =IF(OR(O89="",P89=""),"",(P89-O89)*24)
A90: 89 | B90: Renee White | C90: chelsea84@example.org | D90: 42 | E90: Other | F90: Nikon D | G90: 44409 | H90: Billing inquiry | I90: Product setup | J90: I'm having an issue with the {product_purchased}. Please assist. Product Purchasing Error Product Purchasing Error Yes | No 28 - 30 28 - 30 32 | Product Purchasing Error | Product Purchase Error I've reviewed the troubleshooting steps on the official support website, but they didn't resolve the problem. | K90: Open | M90: Critical | N90: Email | R90: 89 | S90: =PROPER(CustomerSupport[[#This Row],[Resolution]]) | T90: =TRIM(CustomerSupport[[#This Row],[Customer Name]]) -> Renee White | U90: =MONTH(CustomerSupport[[#This Row],[Date of Purchase]]) -> 8 | V90: =TEXT('Working data'!G90,"mmmm") -> August | W90: =YEAR(CustomerSupport[[#This Row],[Date of Purchase]]) -> 2021 | X90: =IF(OR(O90="",P90=""),"",(P90-O90)*24)
A91: 90 | B91: Lisa Hill | C91: hinescarrie@example.org | D91: 40 | E91: Male | F91: Sony Xperia | G91: 43860 | H91: Product inquiry | I91: Product recommendation | J91: I'm having an issue with the {product_purchased}. Please assist. If your computer is connected to a power source, please do not open the {product_purchased}. Please assist. If your router is wired up I've already contacted customer support multiple times, but the issue remains unresolved. | K91: Closed | L91: Exactly red two dog. | M91: Medium | N91: Email | O91: 45077.971 | P91: 45078.132 | Q91: 5 | R91: 90 | S91: =PROPER(CustomerSupport[[#This Row],[Resolution]]) -> Exactly Red Two Dog. | T91: =TRIM(CustomerSupport[[#This Row],[Customer Name]]) -> Lisa Hill | U91: =MONTH(CustomerSupport[[#This Row],[Date of Purchase]]) -> 1 | V91: =TEXT('Working data'!G91,"mmmm") -> January | W91: =YEAR(CustomerSupport[[#This Row],[Date of Purchase]]) -> 2020 | X91: =IF(OR(O91="",P91=""),"",(P91-O91)*24) -> 3.8666667
A92: 91 | B92: Sandra Bass | C92: jamesbaxter@example.com | D92: 57 | E92: Other | F92: Sony Xperia | G92: 44119 | H92: Refund request | I92: Software bug | J92: I've forgotten my password for my {product_purchased} account, and the password reset option is not working. How can I recover my account? - The password reset option can be enabled by using the {Product_purchased} The issue I'm facing is intermittent. Sometimes it works fine, but other times it acts up unexpectedly. | K92: Pending Customer Response | M92: High | N92: Phone | O92: 45078.303 | R92: 91 | S92: =PROPER(CustomerSupport[[#This Row],[Resolution]]) | T92: =TRIM(CustomerSupport[[#This Row],[Customer Name]]) -> Sandra Bass | U92: =MONTH(CustomerSupport[[#This Row],[Date of Purchase]]) -> 10 | V92: =TEXT('Working data'!G92,"mmmm") -> October | W92: =YEAR(CustomerSupport[[#This Row],[Date of Purchase]]) -> 2020 | X92: =IF(OR(O92="",P92=""),"",(P92-O92)*24)
A93: 92 | B93: Madeline Osborne | C93: tyler12@example.net | D93: 62 | E93: Male | F93: iPhone | G93: 44514 | H93: Product inquiry | I93: Display issue | J93: I'm having an issue with the {product_purchased}. Please assist. (Beware when I accidentally add a link to your product and the item you selected incorrectly, you may see some data about missing items and it may require This problem started occurring after the recent software update. I haven't made any other changes to the device. | K93: Pending Customer Response | M93: Low | N93: Email | O93: 45078.01 | R93: 92 | S93: =PROPER(CustomerSupport[[#This Row],[Resolution]]) | T93: =TRIM(CustomerSupport[[#This Row],[Customer Name]]) -> Madeline Osborne | U93: =MONTH(CustomerSupport[[#This Row],[Date of Purchase]]) -> 11 | V93: =TEXT('Working data'!G93,"mmmm") -> November | W93: =YEAR(CustomerSupport[[#This Row],[Date of Purchase]]) -> 2021 | X93: =IF(OR(O93="",P93=""),"",(P93-O93)*24)
A94: 93 | B94: Sydney Wagner | C94: paul73@example.com | D94: 44 | E94: Male | F94: Bose QuietComfort | G94: 44343 | H94: Technical issue | I94: Peripheral compatibility | J94: I'm having an issue with the {product_purchased}. Please assist. Here are some additional notes about using the product in order to purchase the product: The "new" name of the product is used. This name I've noticed a sudden decrease in battery life on my {product_purchased}. It used to last much longer. | K94: Pending Customer Response | M94: Low | N94: Email | O94: 45078.665 | R94: 93 | S94: =PROPER(CustomerSupport[[#This Row],[Resolution]]) | T94: =TRIM(CustomerSupport[[#This Row],[Customer Name]]) -> Sydney Wagner | U94: =MONTH(CustomerSupport[[#This Row],[Date of Purchase]]) -> 5 | V94: =TEXT('Working data'!G94,"mmmm") -> May | W94: =YEAR(CustomerSupport[[#This Row],[Date of Purchase]]) -> 2021 | X94: =IF(OR(O94="",P94=""),"",(P94-O94)*24)
A95: 94 | B95: Jeremy Good | C95: michael25@example.net | D95: 32 | E95: Female | F95: PlayStation | G95: 44340 | H95: Refund request | I95: Installation support | J95: I'm having an issue with the {product_purchased}. Please assist. In-app purchases don't always match up with your new product. In-app purchases are very costly. Make sure you also check if your product is I've noticed a peculiar error message popping up on my {product_purchased} screen. It says '{error_message}'. What does it mean? | K95: Open | M95: Low | N95: Email | R95: 94 | S95: =PROPER(CustomerSupport[[#This Row],[Resolution]]) | T95: =TRIM(CustomerSupport[[#This Row],[Customer Name]]) -> Jeremy Good | U95: =MONTH(CustomerSupport[[#This Row],[Date of Purchase]]) -> 5 | V95: =TEXT('Working data'!G95,"mmmm") -> May | W95: =YEAR(CustomerSupport[[#This Row],[Date of Purchase]]) -> 2021 | X95: =IF(OR(O95="",P95=""),"",(P95-O95)*24)
A96: 95 | B96: Scott Estrada | C96: davidcox@example.org | D96: 65 | E96: Other | F96: Microsoft Xbox Controller | G96: 44536 | H96: Product inquiry | I96: Account access | J96: I'm having an issue with the {product_purchased}. Please assist. </name> <product_purchased_url >http://www.kyle@junebug.com/tutorial/cure-all- I've tried troubleshooting steps mentioned in the user manual, but the issue persists. | K96: Open | M96: Critical | N96: Phone | R96: 95 | S96: =PROPER(CustomerSupport[[#This Row],[Resolution]]) | T96: =TRIM(CustomerSupport[[#This Row],[Customer Name]]) -> Scott Estrada | U96: =MONTH(CustomerSupport[[#This Row],[Date of Purchase]]) -> 12 | V96: =TEXT('Working data'!G96,"mmmm") -> December | W96: =YEAR(CustomerSupport[[#This Row],[Date of Purchase]]) -> 2021 | X96: =IF(OR(O96="",P96=""),"",(P96-O96)*24)
A97: 96 | B97: Linda Campbell | C97: davisnatalie@example.net | D97: 60 | E97: Male | F97: Autodesk AutoCAD | G97: 44471 | H97: Product inquiry | I97: Battery life | J97: My {product_purchased} crashed, and I lost all the data stored on it. Is there any way to recover the lost data? Is there any way to recover the lost data? Can it be done remotely from a remote I've noticed a peculiar error message popping up on my {product_purchased} screen. It says '{error_message}'. What does it mean? | K97: Closed | L97: Series special into hour feel stuff. | M97: High | N97: Chat | O97: 45078.006 | P97: 45078.778 | Q97: 5 | R97: 96 | S97: =PROPER(CustomerSupport[[#This Row],[Resolution]]) -> Series Special Into Hour Feel Stuff. | T97: =TRIM(CustomerSupport[[#This Row],[Customer Name]]) -> Linda Campbell | U97: =MONTH(CustomerSupport[[#This Row],[Date of Purchase]]) -> 10 | V97: =TEXT('Working data'!G97,"mmmm") -> October | W97: =YEAR(CustomerSupport[[#This Row],[Date of Purchase]]) -> 2021 | X97: =IF(OR(O97="",P97=""),"",(P97-O97)*24) -> 18.516667
A98: 97 | B98: Charles Simpson | C98: vanessa39@example.net | D98: 18 | E98: Female | F98: Roomba Robot Vacuum | G98: 44129 | H98: Cancellation request | I98: Battery life | J98: I'm facing a problem with my {product_purchased}. The {product_purchased} is not turning on. It was working fine until yesterday, but now it doesn't respond. I'm thinking maybe they have a bug. I'm concerned about the security of my {product_purchased} and would like to ensure that my data is safe. | K98: Open | M98: High | N98: Social media | R98: 97 | S98: =PROPER(CustomerSupport[[#This Row],[Resolution]]) | T98: =TRIM(CustomerSupport[[#This Row],[Customer Name]]) -> Charles Simpson | U98: =MONTH(CustomerSupport[[#This Row],[Date of Purchase]]) -> 10 | V98: =TEXT('Working data'!G98,"mmmm") -> October | W98: =YEAR(CustomerSupport[[#This Row],[Date of Purchase]]) -> 2020 | X98: =IF(OR(O98="",P98=""),"",(P98-O98)*24)
A99: 98 | B99: Dan Newton | C99: deleonedward@example.net | D99: 22 | E99: Other | F99: Xbox | G99: 43848 | H99: Product inquiry | I99: Delivery problem | J99: I've recently set up my {product_purchased}, but it fails to connect to any available networks. What steps should I take to troubleshoot this issue? Step 1: You need to make sure that the DNS query you I've reviewed the troubleshooting steps on the official support website, but they didn't resolve the problem. | K99: Pending Customer Response | M99: High | N99: Email | O99: 45078.08 | R99: 98 | S99: =PROPER(CustomerSupport[[#This Row],[Resolution]]) | T99: =TRIM(CustomerSupport[[#This Row],[Customer Name]]) -> Dan Newton | U99: =MONTH(CustomerSupport[[#This Row],[Date of Purchase]]) -> 1 | V99: =TEXT('Working data'!G99,"mmmm") -> January | W99: =YEAR(CustomerSupport[[#This Row],[Date of Purchase]]) -> 2020 | X99: =IF(OR(O99="",P99=""),"",(P99-O99)*24)
A100: 99 | B100: Nichole Huang | C100: sheryldawson@example.org | D100: 38 | E100: Male | F100: Samsung Galaxy | G100: 44083 | H100: Billing inquiry | I100: Refund request | J100: I'm having an issue with the {product_purchased}. Please assist. <s3> Please provide the product name, location and shipping address in the Product Overview. <s3> This message will be unread for 12 seconds. I've recently updated the firmware of my {product_purchased}, and the issue started happening afterward. Could it be related to the update? | K100: Closed | L100: Generation officer force test evening certain sign oil. | M100: High | N100: Chat | O100: 45078.296 | P100: 45078.615 | Q100: 5 | R100: 99 | S100: =PROPER(CustomerSupport[[#This Row],[Resolution]]) -> Generation Officer Force Test Evening Certain Sign Oil. | T100: =TRIM(CustomerSupport[[#This Row],[Customer Name]]) -> Nichole Huang | U100: =MONTH(CustomerSupport[[#This Row],[Date of Purchase]]) -> 9 | V100: =TEXT('Working data'!G100,"mmmm") -> September | W100: =YEAR(CustomerSupport[[#This Row],[Date of Purchase]]) -> 2020 | X100: =IF(OR(O100="",P100=""),"",(P100-O100)*24) -> 7.6666667
...

Sheet Audit check
A2: Duplicate Ticket IDs found | B2: No
A3: Total CSAT blanks | B3: =COUNTBLANK('Working data'!Q2:Q8470) -> 5700
A4: Total CSAT filled | B4: =COUNTA('Working data'!Q2:Q8470) -> 2769
A5: Blank percentage | B5: =B3/(B3+B4)*100/100 -> 0.67304286
A6: Trim Applied | B6: Yes
H28: x

Sheet KPI_Summary
A2: Total Tickets | B2: =COUNTA(CustomerSupport[Ticket ID]) -> 8469
A3: Open Tickets | B3: =COUNTIF('Working data'!K:K,"Open") -> 2819
A4: Closed Tickets | B4: =COUNTIF('Working data'!K:K,"Closed") -> 2769
A5: Pending Tickets | B5: =COUNTIF('Working data'!K:K,"Pending Customer Response") -> 2881
A6: Avg CSAT Score | B6: =AVERAGE('Working data'!Q2:Q8470) -> 2.9913326

Sheet Analysis Sheet
A3: Row Labels | B3: Count of Ticket ID
A4: Closed | B4: 1366
A5: Open | B5: 1433
A6: Pending Customer Response | B6: 1434
A7: Grand Total | B7: 4233
A15: Row Labels | B15: Count of Ticket ID
A16: Billing inquiry | B16: 832
A17: Cancellation request | B17: 845
A18: Product inquiry | B18: 794
A19: Refund request | B19: 854
A20: Technical issue | B20: 908
A21: Grand Total | B21: 4233

Sheet Dashboard
A1: Customer Support Ticket Dashboard
A6: Total Tickets | D6: Open Tickets | G6: Closed Tickets | J6: Pending Tickets | M6: Avg CSAT Score
A8: =KPI_Summary!B2 -> 8469 | D8: =KPI_Summary!B3 -> 2819 | G8: =KPI_Summary!B4 -> 2769 | J8: =KPI_Summary!B5 -> 2881 | M8: =KPI_Summary!B6 -> 2.9913326
